Workbook

Sheet Base de Dados
A1: TABELA GERAL DE REGISTROS
A2: Nº REGISTRO | B2: VIGÊNCIA | C2: DATA | D2: MODALIDADE | E2: NOME INSTITUCIONAL | F2: NOME FANTASIA | G2: CNPJ Matriz | H2: CNPJ Filial | I2: PROGRAMA | J2: RES | K2: CONVÊNIO | L2: ENDEREÇO DO PROGRAMA | M2: CEP | N2: BAIRRO | O2: SUBPREFEITURA | P2: REGIÃO | Q2: TELEFONE | R2: E-MAIL | S2: SITE | T2: CAPACIDADE | U2: ATENDIDOS | V2: SEI | W2: Para encerramento | X2: ID
A3: 001/12 | B3: 4 (quatro) anos | C3: 46705 | D3: OSC | E3: ASSOCIAÇÃO SANTO AGOSTINHO - ASA | F3: CDI LAR SANTO ALBERTO | G3: 62.272.497/0001-54 | H3: 62.272.497/0010-45 | I3: CDI | J3: 9 | K3: SMADS | L3: Rua Professor Dorival Dias Minhoto, n° 231 | M3: 02435-090 | N3: Santana | O3: Santana/Tucuruvi | P3: Norte | Q3: (11) 2236-1418 | R3: asa@asatransforma.org.br | S3: www.asatransforma.org.br | T3: 31 | U3: 31 | V3: 6074.2023/0009887-0 | X3: 1
A4: 001.2/12 | B4: NÃO RENOVADO | C4: 46036 | D4: OSC | E4: ASSOCIAÇÃO SANTO AGOSTINHO - ASA | F4: INCLUSÃO DIGITAL PARA PESSOAS IDOSAS | G4: 62.272.497/0001-54 | H4: 62.272.497/0001-54 | I4: PROJETOS | J4: 12 | K4: FMID | L4: Professor Dorival Dias Minhoto, 231 | N4: Lausane Paulista | O4: Santana/Tucuruvi | P4: Norte | R4: thais.certain@asatrasnforma.org.br | S4: www.asatransforma.org.br | T4: 36 | U4: 36 | V4: 6074.2023/0009887-0 | X4: 2
A5: 002/12 | B5: NÃO RENOVADO | C5: 43390 | D5: OSC | E5: ASSOCIAÇÃO DOS FAMILIARES E AMIGOS DOS IDOSOS - AFAI | G5: 07.852.256/0001-76 | I5: CDI | O5: Vila Mariana | P5: Sul | R5: afaicdi@hotmail.com | X5: 3
A6: 003.1/12 | B6: 2 (dois) anos | C6: 46675 | D6: OSC | E6: ASSOCIAÇÃO FRANCISCANA DE SOLIDARIEDADE | F6: CASA DE CLARA | G6: 11.861.086/0001-63 | H6: 11.861.086/0013-05 | I6: NCI | J6: 8 | K6: Não | L6: Rua Serra de Jairé, n° 316 | M6: 03175-010 | N6: Belém | O6: Mooca | P6: Leste | Q6: (11) 2604-5688 | R6: sefras@sefras.org.br | S6: www.sefras.org.br | T6: 200 | U6: 170 | V6: 6074.2025/0007896-2 | X6: 4
A7: 003.2/12 | B7: NÃO RENOVADO | C7: 45802 | D7: OSC | E7: ASSOCIAÇÃO FRANCISCANA DE SOLIDARIEDADE - SEFRAS | F7: CASA DE CLARA | G7: 11.861.086/0001-63 | I7: CDI | J7: 9 | K7: SMADS | L7: Rua Serra de Jairé, n° 316 | M7: 03175-010 | N7: Belém | O7: Mooca | P7: Leste | Q7: 2604-5688 | R7: articulacao@sefras.org.br | S7: www.sefras.org.br | T7: 30 | U7: 29 | V7: Não possui | X7: 5
A8: 004.1/13 | B8: 4 (quatro) anos | C8: 47090 | D8: OSC | E8: SOCIEDADE BENEFICENTE EQUILIBRIO DE INTERLAGOS - SOBEI | F8: NCI IMBUIAS | G8: 53.818.191/0001-60 | H8: 53.818.191/0011-31 | I8: NCI | J8: 7 | K8: SMADS | L8: Rua Santo Antônio do Cântaro, 32 | M8: 04829-090 | N8: Jardim Bela Vista | O8: Capela do Socorro | P8: Sul | Q8: (11) 5973-6034 | R8: sobei@sobei.org.com.br | S8: www.sobei.org.br | T8: 200 | U8: 200 | V8: 6074.2024/0009788-4 | X8: 6
A9: 004.2/13 | B9: NÃO RENOVADO | C9: 43820 | D9: OSC | E9: SOCIEDADE BENEFICENTE EQUILIBRIO DE INTERLAGOS - SOBEI | F9: MONTANARO | G9: 53.818.191/0001-60 | H9: 53.818.191/0007-55 | I9: NCI | O9: Capela do Socorro | P9: Sul | R9: sobei@sobei.org.br | S9: www.sobei.org.br | X9: 7
A10: 004.3/13 | B10: NÃO RENOVADO | C10: 45643 | D10: OSC | E10: SOCIEDADE BENEFICENTE EQUILIBRIO DE INTERLAGOS - SOBEI | G10: 53.818.191/0001-60 | H10: 53.818.191/0020-22 | I10: ILPI | O10: Parelheiros | P10: Sul | R10: sobei@sobei.org.br | S10: www.sobei.org.br | X10: 8
A11: 004.4/13 | B11: 4 (quatro) anos | C11: 46582 | D11: OSC | E11: SOCIEDADE BENEFICENTE EQUILIBRIO DE INTERLAGOS - SOBEI | F11: CCINTER ANTONIO CARLOS CARUSO | G11: 53.818.191/0001-60 | H11: 53.818.191/0023-75 | I11: CCINTER | J11: 11 | K11: SMADS | L11: Rua Angelina Regolim Cardoso de Mendonça, n° 51 | M11: 04811-150 | N11: Jardim Régis | O11: Capela do Socorro | P11: Sul | Q11: (11) 5666-0242 | R11: sobei@sobei.org.br | S11: www.sobei.org.br | T11: 240 | U11: 240 | V11: 6074.2023/0006498-4 | X11: 9
A12: 005/13 | B12: NÃO RENOVADO | C12: 43820 | D12: OSC | E12: INSTITUTO SOCIAL, EDUCATIVO E BENEFICENTE NOVO SIGNO | G12: 78.636.974-0004-04 | I12: NCI | O12: Vila Mariana | P12: Sul | R12: msemanovosigno@uol.com.br | X12: 10
A13: 006/13 | B13: 4 (quatro) anos | C13: 46320 | D13: Particular | E13: PENSÃO NEW HEAVEN LTDA | F13: CASA DE REPOUSO NEW HEAVEN | G13: 02.345.462/0001-76 | I13: ILPI | J13: 3 | K13: Não | L13: Av Diogenes Ribeiro de Lima, 1768 | M13: 05.458-001 | N13: Alto de Pinheiros | O13: Pinheiros | P13: Oeste | Q13: (11) 3022-3902 | R13: contato.newheavenresidencialsr@gmail.com | S13: www.newheavenresidencialsenior.com | T13: 21 | U13: 17 | V13: 6074.2022/0007128-8 | X13: 11
A14: 007/13 | B14: 2 (dois) anos | C14: 46389 | D14: OSC | E14: ASSOCIAÇÃO DE ASSISTÊNCIA À CRIANÇA DEFICIENTE | F14: REABILITAÇÃO PARA IDOSOS COM DEFICIÊNCIA FÍSICA | G14: 60.979.457/0001-11 | H14: 60.979.457/0001-11 | I14: PROJETOS | J14: 12 | K14: Não | L14: Rua Professor Ascendino Reis, 724 | M14: 04027-000 | N14: Vila Clementino | O14: Vila Mariana | P14: Sul | Q14: (11) 5576-0769 | R14: prestacaodecontas@aacd.org.br | S14: www.aacd.org.br | T14: 7000 | U14: 900 | V14: 6074.2022/0007575-5 | X14: 12
A15: 008/13 | B15: 4 (quatro) anos | C15: 47268 | D15: Particular | E15: CASA DE REPOUSO RECANTO DAS ARAUCÁRIAS LTDA | F15: RESIDENCIAL DAS ARAUCÁRIAS | G15: 54.232.381/0001-63 | H15: 54.232.381/0001-63 | I15: ILPI | J15: 3 | K15: Não | L15: Rua dos Lírios, n° 282 | M15: 04047-040 | N15: Mirandópolis | O15: Vila Mariana | P15: Sul | Q15: (11) 2275-3078 | R15: pauloievorlino@terra.com.br | T15: 20 | U15: 18 | V15: 6074.2025/0003802-2 | X15: 13
A16: 009/13 | B16: 4 (quatro) anos | C16: 47315 | D16: OSC | E16: CENTRO DE PROMOÇÃO HUMANA LAR VICENTINO | F16: LAR VICENTINO | G16: 48.956.742/0001-11 | H16: 48.956.742/0001-11 | I16: ILPI | J16: 6 | K16: Não | L16: Rua Ovídio Lopes, n° 253 | M16: 03804-110 | N16: Ermelino Matarazzo | O16: Ermelino Matarazzo | P16: Leste | Q16: (11) 2546-5682 | R16: adminsitracao@larvicentino.org.br | S16: www.larvicentino.org.br | T16: 40 | U16: 35 | V16: 6074.2025/0005703-5 | X16: 14
A17: 010/13 | B17: 4 (quatro) anos | C17: 46980 | D17: Particular | E17: UNIGER - UNIDADE DE INTERNAÇÃO GERIÁTRICA LTDA | F17: RESIDENCIAL TONIOLO MEMORY CARE | G17: 07.463.596/0001-05 | H17: 07.463.596/0001-05 | I17: ILPI | J17: 3 | K17: Não | L17: Rua Dona Brígida, 671 | M17: 04111-081 | N17: Vila Mariana | O17: Vila Mariana | P17: Sul | Q17: (11) 3663-9060 / (11) 99316-6700 | R17: enfermeira.karen@residencialtoniolo.com.br | S17: www.residencialtoniolo.com.br | T17: 40 | U17: 37 | V17: 6074.2024/0006897-3 | W17: 6074.2022/0003144-8 | X17: 15
A18: 011/14 | B18: 2 (dois) anos | C18: 46359 | D18: OSC | E18: SINDICATO NACIONAL DOS APOSENTADOS, PENSIONISTAS E IDOSOS DA FORÇA SINDICAL | F18: CENTRO DE CONVIVÊNCIA, CIDADANIA E DEFESA DE DIREITOS DA PESSOA IDOSA | G18: 04.040.532/0001-03 | H18: 04.040.532/0001-03 | I18: PROJETOS | J18: 12 | K18: Não | L18: Rua do Carmo, 171 | M18: 01019-020 | N18: Sé | O18: Sé | P18: Centro | Q18: (11) 3293-7500 | R18: presidente@sindicatodosaposentados.org.br | S18: www.sindicatodosaposentados.org.br | T18: 84000 | U18: 50000 | V18: 6074.2024/0009788-4 | X18: 16
A19: 012.1/14 | B19: 4 (quatro) anos | C19: 47642 | D19: Particular | E19: CASA DE REPOUSO PARA IDOSOS RESIDENCIAL HARMONIA LTDA. | F19: RESIDENCIAL HARMONIA | G19: 07.403.676/0001-75 | H19: 07.403.676/0001-75 | I19: ILPI | J19: 3 | K19: Não | L19: Rua Conde de Porto Alegre, 1855 | M19: 04608-003 | N19: Campo Belo | O19: Santo Amaro | P19: Sul | Q19: (11) 5042-0858 | R19: juliane@residencialharmonia.com.br | S19: www.residencialharmonia.com.br | T19: 23 | U19: 18 | V19: 6074.2022/0000275-8 | X19: 17
A20: 012.2/14 | B20: NÃO RENOVADO | C20: 42471 | D20: Particular | E20: CASA DE REPOUSO PARA IDOSOS RESIDENCIAL HARMONIA LTDA. UNIDADE II (FILIAL) | G20: 07.403.676/0001-75 | I20: ILPI | J20: 3 | K20: Não | O20: Santo Amaro | P20: Sul | R20: contato@residencialharmonia.com.br | X20: 18
A21: 013/14 | B21: 2 (dois) anos | C21: 46478 | D21: Particular | E21: RECANTO DO IDOSO ANHANGUERA LTDA | F21: RECANTO DO IDOSO ANHANGUERA | G21: 04.256.978/0001-70 | H21: 04.256.978/0001-70 | I21: ILPI | J21: 3 | K21: Não | L21: Rod. Anhanguera, KM 21.5 | M21: 05275-000 | N21: Perus | O21: Perus/Anhanguera | P21: Norte | Q21: (11) 5198-4168 | R21: idoso@recantodoidoso.com.br | S21: www.recantodoidoso.com.br | T21: 26 | U21: 21 | V21: 6074.2023/0001561-4 | X21: 19
A22: 014/14 | B22: NÃO RENOVADO | C22: 45186 | D22: Particular | E22: SOLAR PRIMAVERA S/S LTDA - ME | G22: 03.671.916/0001-61 | I22: ILPI | J22: 3 | K22: Não | O22: Vila Maria/Vila Guilherme | P22: Norte | R22: helenaportugal@ibest.com.br | X22: 20
A23: 015.1/14 | B23: 4 (quatro) anos | C23: 47615 | D23: Particular | E23: MARLENE DE FÁTIMA MENDES | F23: CASA DE REPOUSO PÔR DO SOL | G23: 72.815.863/0001-28 | H23: 72.815.863/0001-28 | I23: ILPI | J23: 3 | K23: Não | L23: Rua Décio Reis, 492 | M23: 05446-010 | N23: Alto de Pinheiros | O23: Pinheiros | P23: Oeste | Q23: (11) 3814-6643 | R23: contato@casaderepousopordosol.com.br | S23: www.casaderepousopordosol.com.br | T23: 30 | U23: 26 | V23: 6074.2021/0008537-6 | X23: 21
A24: 015.2/14 | B24: 4 (quatro) anos | C24: 47026 | D24: Particular | E24: MARLENE DE FÁTIMA MENDES - EPP | F24: CASA DE REPOUSO ELITE | G24: 72.815.863/0001-28 | H24: 72.815.863/0002-09 | I24: ILPI | J24: 3 | K24: Não | L24: Rua Doutor Franco da Rocha, 50 | M24: 05015-040 | N24: Perdizes | O24: Lapa | P24: Oeste | Q24: (11) 3862-7836 | R24: fernandaprizon@ig.com.br | S24: www.casaderepousoelite | T24: 30 | U24: 26 | V24: 6074.2024/0007807-3 | X24: 22
A25: 016/14 | B25: 4 (quatro) anos | C25: 46848 | D25: Particular | E25: ALVORADA NOVA CASA DE REPOUSO LTDA | G25: 17.569.752/0001-70 | H25: 17.569.752/0001-70 | I25: ILPI | J25: 3 | K25: Não | L25: Rua Nova Jerusalém, n° 504 | M25: 03410-000 | N25: Tatuapé | O25: Mooca | P25: Leste | Q25: (11) 3895-0746 | R25: e.amorim.ribeiro@bol.com.br | T25: 23 | U25: 21 | V25: 6074.2024/0003245-6 | X25: 23
A26: 017/14 | B26: NÃO RENOVADO | C26: 44786 | D26: Particular | E26: RESIDENCIAL ALTO DA BOA VISTA PARA IDOSOS LTDA - ME | G26: 10.248.923/0001-10 | I26: ILPI | J26: 3 | K26: Não | O26: Santo Amaro | P26: Sul | R26: crirahal@ig.com.br | X26: 24
A27: 018/14 | B27: NÃO RENOVADO | C27: 44844 | D27: Particular | E27: UNIDADE GERONTOLÓGICA FERREIRA LTDA - ME - UNIDADE I | G27: 06.997.875/0001-96 | I27: ILPI | J27: 3 | K27: Não | L27: Rua Tirana, 26 | M27: 03.359-110 | N27: Vila Formosa | O27: Aricanduva/Formosa/Carrão | P27: Leste | Q27: (11) 2674 9131 | R27: ugf@ugerontologica.com.br | X27: 25
A28: 018/14 | B28: NÃO RENOVADO | C28: 42582 | D28: Particular | E28: UNIDADE GERONTOLÓGICA FERREIRA LTDA - ME - UNIDADE II (FILIAL) | G28: 06.997.875/0002-77 | I28: ILPI | J28: 3 | K28: Não | N28: Vila Formosa | O28: Aricanduva/Formosa/Carrão | P28: Leste | Q28: (11) 2674-9131 | R28: ugf@ugerontologica.com.br | X28: 26
A29: 019/14 | B29: 4 (quatro) anos | C29: 46617 | D29: Particular | E29: CASA DE REPOUSO LUZ DA MANHÃ SS LTDA | G29: 00.738.764/0001-89 | H29: 00.738.764/0001-89 | I29: ILPI | J29: 3 | K29: Não | L29: Rua Hugo Carotini, n° 567 | M29: 05532-020 | N29: Jd. Previdência | O29: Butantã | P29: Oeste | Q29: (11) 3721-3075 | R29: casaderepousoluzdamanha@gmail.com | T29: 15 | U29: 10 | V29: 6074.2023/0007539-0 | X29: 27
A30: 020.1/14 | B30: 4 (quatro) anos | C30: 46238 | D30: OSC | E30: CROPH - COORDENAÇÃO REGIONAL DAS OBRAS DE PROMOÇÃO HUMANA | F30: ILPI CANINDÉ | G30: 43.473.487/0001-32 | H30: 43.473.487/0021-86 | I30: ILPI | J30: 5 | K30: SMADS | L30: Rua Comendador Nestor Pereira, 77 | M30: 03.034-070 | N30: Pari | O30: Mooca | P30: Leste | Q30: (11) 3228-1873 | R30: adm.croph@gmail.com | S30: croph@uol.com.br | T30: 60 | U30: 53 | V30: 6074.2022/0005338-7 | X30: 28
A31: 020.2/14 | B31: 4 (quatro) anos | C31: 46238 | D31: OSC | E31: CROPH - COORDENAÇÃO REGIONAL DAS OBRAS DE PROMOÇÃO HUMANA | F31: ILPI SANTANA | G31: 43.473.487/0001-32 | H31: 43.473.487/0034-09 | I31: ILPI | J31: 5 | K31: SMADS | L31: Rua Capitão Sérvio Rodrigues Caldas, 143 | M31: 02.244-040 | N31: Parada Inglesa | O31: Santana/Tucuruvi | P31: Norte | Q31: (11) 2337-0704 | S31: croph@uol.com.br | T31: 30 | U31: 30 | V31: 6074.2022/0005338-7 | X31: 29
A32: 020.3/14 | B32: NÃO RENOVADO | C32: 43906 | D32: OSC | E32: CROPH - COORDENAÇÃO REGIONAL DE OBRAS DE PROMOÇÃO HUMANA | F32: SÍTIO DAS ALAMEDAS | G32: 43.473.487/0001-32 | H32: 43.473.487/0020-03 | I32: CAEI | J32: 10 | K32: SMADS | O32: Sé | P32: Centro | S32: croph@uol.com.br | X32: 30
A33: 020.4/14 | B33: 4 (quatro) anos | C33: 46238 | D33: OSC | E33: CROPH - COORDENAÇÃO REGIONAL DAS OBRAS DE PROMOÇÃO HUMANA | F33: CRECI | G33: 43.473.487/0001-32 | H33: 43.473.487/0014-57 | I33: NCI | J33: 7 | K33: SMADS | L33: Rua Formosa, 215 | M33: 01.049-000 | N33: Anhangabaú | O33: Sé | P33: Centro | Q33: (11) 3258-4376 | S33: croph@uol.com.br | T33: 400 | U33: 524 | V33: 6074.2022/0005338-7 | X33: 31
A34: 020.5/14 | B34: 4 (quatro) anos | C34: 46889 | D34: OSC | E34: CROPH - COORDENAÇÃO REGIONAL DAS OBRAS DE PROMOÇÃO HUMANA | F34: ILPI TULIPAS MOOCA | G34: 43.473.487/0001-32 | H34: 43.473.487/0041-20 | I34: ILPI | J34: 5 | K34: SMADS | L34: Rua Florianópolis, n° 184 | M34: 03185-050 | N34: Mooca | O34: Mooca | P34: Leste | Q34: (11) 2606-6360 | R34: adm.croph@gmail.com | S34: croph@uol.com.br | T34: 30 | U34: 30 | V34: 6074.2024/0004543-4 | X34: 32
A35: 020.6/14 | B35: 4 (quatro) anos | C35: 47268 | D35: OSC | E35: CROPH - COORDENAÇÃO REGIONAL DAS OBRAS DE PROMOÇÃO HUMANA | F35: CAEI - CASA VERDE | G35: 43.473.487/0001-32 | H35: 43.473.487/0001-32 | I35: CAEI | J35: 10 | K35: SMADS | L35: Rua Antonio Vera Cruz, 213 | M35: 02555-010 | N35: Casa Verde | O35: Casa Verde/Cachoeirinha/Limão | P35: Norte | Q35: (11) 3955-2121/3965-6006 | R35: adm.croph@uol.com.br | S35: www.croph.org.br | T35: 60 | U35: 60 | V35: 6074.2025/0004066-3 | X35: 33
A36: 021/14 | B36: 2 (dois) anos | C36: 46512 | D36: OSC | E36: ASSOCIAÇÃO NIPO-BRASILEIRA DE ASSISTÊNCIA SOCIAL - ENKYO | F36: NÚCLEO DE CONVIVÊNCIA PARA IDOSOS | G36: 21.161.900/0001-90 | H36: 21.161.900/0001-90 | I36: NCI | J36: 8 | K36: Não | L36: Rua Fagundes, n° 121 - 3° andar | M36: 01508-030 | N36: Liberdade | O36: Sé | P36: Centro | Q36: (11) 3274-6518 | R36: social@enkyo.org.br | S36: www.enkyo.org.br | T36: 80 | U36: 330 | V36: 6074.2023/0003862-2 | X36: 34
A37: 022/14 | B37: 4 (quatro) anos | C37: 46477 | D37: Particular | E37: RELUZ HOSPEDAGEM PARA IDOSOS LTDA_x000D_ ANTIGO: RENATA LUCAS GIOSA HOSPEDAGEM PARA IDOSOS - ME | F37: LAR RESIDENCIAL RELUZ | G37: 08.364.900/0001-20 | H37: 08.364.900/0001-20 | I37: ILPI | J37: 3 | K37: Não | L37: Rua Franco Paulista, n° 181 | M37: 02332-030 | N37: Água Fria | O37: Santana/Tucuruvi | P37: Norte | Q37: (11) 2950-5497 | R37: residencialreluz@hotmail.com | T37: 28 | U37: 19 | V37: 6074.2023/0002783-3 | X37: 35
A38: 023/14 | B38: 4 (quatro) anos | C38: 1º/12/2027 | D38: OSC | E38: INSTITUTO BRASILEIRO FILHAS DE SÃO CAMILO | F38: INSTITUIÇÃO DE LONGA PERMANÊNCIA PARA IDOSOS SÃO CAMILO | G38: 12.920.752/0001-50 | H38: 12.920.752/0002-30 | I38: ILPI | J38: 6 | K38: Não | L38: Rua Adelino Bertoli, n° 139 | M38: 02241-120 | N38: Vl. Dom Pedro II | O38: Santana/Tucuruvi | P38: Norte | Q38: (11) 2973-0813 | R38: administracao@filhasdesaocamilo.com.br | S38: www.filhasdesaocamilo.com.br | T38: 80 | U38: 80 | V38: 6074.2023/0011032-3 | X38: 36
A39: 024/15 | B39: 4 (quatro) anos | C39: 46826 | D39: Particular | E39: CASA DE REPOUSO ANA NERY LTDA | F39: CASA DE REPOUSO ANA NERY | G39: 01.607.265/0001-15 | H39: 01.607.265/0001-15 | I39: ILPI | J39: 3 | K39: Não | L39: Rua Dr. Alberto Bentro, n° 742 | M39: 04750-001 | N39: Santo Amaro | O39: Santo Amaro | P39: Sul | Q39: (11) 5686-2215 | R39: casaderepousoananery@hotmail.com | S39: www.casaderepousoananery;com.br | T39: 27 | U39: 24 | X39: 37
A40: 025/15 | B40: 2 (dois) anos | C40: 46249 | D40: OSC | E40: ASSOCIAÇÃO BENEFICENTE DE AMPARO AO IDOSO CARENTE CAMINHO DA VIDA | F40: CAMINHO DA VIDA | G40: 03.692.295/0001-00 | H40: 03.692.295/0001-00 | I40: ILPI | J40: 6 | K40: Não | L40: Avenida Doutor Bernardino Brito Fonseca de Carvalho, 2257 | M40: 03535-000 | N40: Jardim Samara | O40: Penha | P40: Leste | Q40: (11) 2748-7811 / (11) 99990-0083 | R40: administração@abaic.com.br e abaic.caminhodavida@gmail.com | S40: www.abaic.com.br | T40: 20 | U40: 10 | V40: 6074.2022/0000732-6 | X40: 38
A41: 026/15 | B41: 4 (quatro) anos | C41: 47026 | D41: OSC | E41: ASSOCIAÇÃO BENEFICENTE MERCEDÁRIA SANTO ANTÔNIO | F41: LAR NOSSA SENHORA DAS MERCÊS | G41: 33.642.455/0001-60 | H41: 33.642.455/0025-37 | I41: ILPI | J41: 6 | K41: Não | L41: Rua Dona Elisa de Moraes Mendes, nº 250 | M41: 05449-000 | N41: Alto de Pinheiros | O41: Pinheiros | P41: Oeste | Q41: 3021-5971 | R41: larnsmerces@uol.com.br | S41: www.residencialmerces.com.br | T41: 37 | U41: 34 | V41: 6074.2024/0007661-5 | X41: 39
A42: 027/15 | B42: 4 (quatro) anos | C42: 46629 | D42: Particular | E42: RESIDENCIAL PERDIZES LTDA | F42: RESIDENCIAL PERDIZES | G42: 53.371.308/0001-00 | H42: 53.371.308/0001-00 | I42: ILPI | J42: 3 | K42: Não | L42: Rua Turiassú, n° 566 | M42: 05005-000 | N42: Água Branca | O42: Lapa | P42: Oeste | Q42: (11) 3862-7273 | R42: r.perdizes@hotmail.com | S42: www.clinicaderepousoperdizes.com.br | T42: 36 | U42: 27 | V42: 6074.2023/0008184-6 | X42: 40
A43: 028/15 | B43: 4 (quatro) anos | C43: 47026 | D43: Particular | E43: BEM VIVER INSTITUIÇÃO DE LONGA PERMANÊNCIA PARA IDOSOS LTDA-EPP | F43: RESIDENCIAL BEM VIVER | G43: 08.926.106/0001-22 | H43: 08.926.106/0001-22 | I43: ILPI | J43: 3 | K43: Não | L43: R. Monsenhor Francisco de Paula, 170 | M43: 03504-000 | N43: Vila Aricanduva | O43: Penha | P43: Leste | Q43: (11) 3473-7779 | R43: casaderepousobemviver@gmail.com | S43: www.bemviverparaidosos.com.br | T43: 29 | U43: 27 | V43: 6074.2024/0008249-6 | X43: 41
A44: 029/15 | B44: NÃO RENOVADO | C44: 42822 | D44: Particular | E44: CASA DE REPOUSO VILA LOBOS LTDA-ME | G44: 07.714.288/0001-05 | I44: ILPI | J44: 3 | K44: Não | O44: Sé | P44: Centro | Q44: (11) 2901-2200/ (11) 2901-2200 | R44: henrique.hgfilho@gmail.com | X44: 42
A45: 030/15 | B45: 2 (dois) anos | C45: 46445 | D45: OSC | E45: SOCIEDADE BENEFICENTE ALEMÃ | F45: SBA RESIDENCIAL | G45: 60.794.047/0001-04 | H45: 60.794.047/0001-04 | I45: ILPI | J45: 6 | K45: Não | L45: Rua Dr. Romeo Ferro, n° 246 | M45: 05591-000 | N45: Jd. Bonfiglioli | O45: Butantã | P45: Oeste | Q45: (11) 3724-9740 | R45: cadastro@sbaresidencial.org.br | S45: www.sba-br.org.br | T45: 220 | U45: 160 | V45: 6074.2022/0009523-3 | X45: 43
A46: 031/15 | B46: 4 (quatro) anos | C46: 46564 | D46: OSC | E46: FEDERAÇÃO ESPÍRITA DO ESTADO DE SÃO PAULO | F46: CASA TRANSITÓRIA FABIANO DE CRISTO – LAR BATUÍRA | G46: 61.669.966/0001-00 | H46: 61.669.966/0002-91 | I46: ILPI | J46: 6 | K46: Não | L46: Av. Condessa Elisabete de Robiano, nº 454 | M46: 03704-000 | N46: Belém | O46: Mooca | P46: Leste | Q46: 2797-2999/2797-2990/3188-8383 | R46: feesp@feesp.org.br; presidente@feesp.org.br | S46: www.feesp.org.br | T46: 30 | U46: 24 | V46: 6074.2020/0003670-5 | X46: 44
A47: 032/15 | B47: NÃO RENOVADO | C47: 43603 | D47: Particular | E47: E DA SILVA E PENSIONATO - ME | F47: CASA DE REPOUSO VIVER BEM | G47: 09.685.896/0001-64 | I47: ILPI | J47: 3 | K47: Não | O47: Penha | P47: Leste | Q47: (11) 2037-0751 | R47: eliassilva35@live.com | X47: 45
A48: 033/15 | B48: 4 (quatro) anos | C48: 47450 | D48: Particular | E48: RESIDENCIAL SÊNIOR LTDA. | F48: FAMÍLIA RESIDENCIAL SÊNIOR | G48: 14.976.538/0001-40 | H48: 14.976.538/0001-40 | I48: ILPI | J48: 3 | K48: Não | L48: Rua Professor Frontino Guimarães, 245 | M48: 04017-050 | N48: Vila Mariana | O48: Vila Mariana | P48: Sul | Q48: (11) 5549-5266 | R48: fabiana@residencialsenior.com.br | S48: www.residencialsenior.com.br | T48: 24 | U48: 22 | V48: 6074.2021/0005298-2 | X48: 46
A49: 034.1/15 | B49: 4 (quatro) anos | C49: 47055 | D49: Particular | E49: CASA DE REPOUSO PRÓ-VITA S/A | F49: RESIDENCIAL PRÓ-VITA | G49: 03.999.246/0001-07 | H49: 03.999.246/0001-07 | I49: ILPI | J49: 3 | K49: Não | L49: Rua Iubatinga, 258 | M49: 05716-110 | N49: Vila Andrade | O49: Campo Limpo | P49: Sul | Q49: (11) 3053-9600 | R49: lyse@residencialprovita.com.br | S49: www.residencialprovita.com.br | T49: 219 | U49: 201 | V49: 6074.2024/0008876-1 | X49: 47
A50: 034.2/15 | B50: 4 (quatro) anos | C50: 47055 | D50: Particular | E50: CASA DE REPOUSO PRÓ-VITA S/A | F50: RESIDENCIAL PRÓ-VITA (FILIAL) | G50: 03.999.246/0001-07 | H50: 03.999.246/0002-98 | I50: ILPI | J50: 3 | K50: Não | L50: Rua Doutor Fonseca Brasil, nº 201 | M50: 05716-060 | N50: Vila Andrade | O50: Campo Limpo | P50: Sul | Q50: (11) 3053-9601 | R50: lyse@residencialprovita.com.br | S50: www.residencialprovita.com.br | T50: 135 | U50: 129 | V50: 6074.2024/0008877-0 | X50: 48
A51: 035/15 | B51: NÃO RENOVADO | C51: 43613 | D51: OSC | E51: ASSISTÊNCIA VICENTINA DE VILA MASCOTE – LAR PADRE VICENTE MELILLO | F51: LAR PADRE VICENTE MELILLO | G51: 08.678.355/0001-46 | I51: ILPI | O51: Jabaquara | P51: Sul | R51: administracao@assistenciadevilamascote.org.br | X51: 49
A52: 036/15 | B52: NÃO RENOVADO | C52: 45642 | D52: Particular | E52: CASA DE REPOUSO RECANTO DA TERCEIRA IDADE S/S LTDA | G52: 03.970.254/0001-20 | I52: ILPI | J52: 3 | K52: Não | L52: Rua Armorial, 85 | M52: 04261-070 | N52: Vila Monumento | O52: Ipiranga | P52: Sul | Q52: (11) 2591-3762 | R52: delporto1@hotmail.com | T52: 19 | U52: 12 | V52: 6074.2022/0008059-7 | X52: 50
A53: 037/15 | B53: NÃO RENOVADO | C53: 42896 | D53: OSC | E53: ASSOCIAÇÃO GER-AÇÕES | G53: 09.290.454/0001-19 | I53: PROJETOS | J53: 12 | O53: Sé | P53: Centro | R53: geracoes@geracoes.org.br | X53: 51
A54: 038/15 | B54: 4 (quatro) anos | C54: 46372 | D54: Particular | E54: VIVACE RESIDENCIAL PARA IDOSOS LTDA (ENCERROU AS ATIVIDADES EM SETEMBRO/2024) | G54: 20.496.462/0001-59 | I54: ILPI | J54: 3 | K54: Não | L54: Rua Ministro Ferreira Alves, nº 90 | M54: 05009-060 | N54: Perdizes | O54: Lapa | P54: Oeste | Q54: 5642-4040 | R54: r.forgiarini@orpea.com.br | S54: www.casaderepousovivace.com.br | T54: 116 | U54: 86 | V54: 6074.2022/0008531-9 | X54: 52
A55: 039/15 | B55: 4 (quatro) anos | C55: 47552 | D55: Particular | E55: QUALITÁ ASSISTÊNCIA A SAÚDE LTDA | F55: RESIDENCIAL QUALITÁ | G55: 07.463.506/0001-86 | H55: 07.463.506/0001-86 | I55: ILPI | J55: 3 | K55: Não | L55: Avenida Vereador José Diniz, n° 1.474 | M55: 04604-001 | N55: Santo Amaro | O55: Santo Amaro | P55: Sul | Q55: (11) 3744-4747 / 5184-1106 | R55: adm@residencialqualita.com.br | T55: 55 | U55: 51 | V55: 6074.2023/0001534-7 | X55: 53
A56: 039.2/15 | B56: 4 (quatro) anos | C56: 46446 | D56: Particular | E56: QUALITÁ ASSISTÊNCIA A SAÚDE LTDA | G56: 07.463.506/0001-86 | H56: 07.463.506/0003-48 | I56: ILPI | J56: 3 | K56: Não | L56: Rua Verbo Divino, n° 415 | M56: 04719-001 | N56: Chácara Santo Antônio | O56: Santo Amaro | P56: Sul | Q56: (11) 5183-4413 | R56: adm2@residencialqualita.com.br | T56: 28 | U56: 15 | V56: 6074.2023/0001534-7 | X56: 54
A57: 040.1/15 | B57: 4 (quatro) anos | C57: 47615 | D57: Particular | E57: CASA DE REPOUSO MOOCA SANTA MADALENA LTDA (MATRIZ) | F57: CASA SANTA MADALENA | G57: 15.556.305/0001-51 | H57: 15.556.305/0001-51 | I57: ILPI | J57: 3 | K57: Não | L57: Rua Cristianópolis, nº 395 | M57: 03128-030 | N57: Mooca | O57: Mooca | P57: Leste | Q57: (11) 3624-1137 | R57: adm.residencialsantamadalena@gmail.com | T57: 50 | U57: 42 | V57: 6074.2026/0002357-4 | X57: 55
A58: 040.2/15 | B58: 4 (quatro) anos | C58: 47615 | D58: Particular | E58: CASA DE REPOUSO MOOCA SANTA MADALENA LTDA (FILIAL) | F58: CASA SANTA MADALENA UNIDADE II | G58: 15.556.305/0002-32 | H58: 15.556.305/0002-32 | I58: ILPI | J58: 3 | K58: Não | L58: Rua Cristianópolis, nº 316 | M58: 03128-030 | N58: Mooca | O58: Mooca | P58: Leste | Q58: (11) 4323-7426 | R58: adm.residencialsantamadalena2@gmail.com | T58: 38 | U58: 36 | V58: 6074.2026/0002357-4 | X58: 56
A59: 041/15 | B59: NÃO RENOVADO | C59: 45970 | D59: Particular | E59: VILA DEL POZZO INSTITUIÇÃO DE LONGA PERMANÊNCIA PARA IDOSOS LTDA | F59: VILLA DEL POZO | G59: 17.322.040/0001-52 | I59: ILPI | J59: 3 | K59: Não | L59: PC Haroldo Daltro, 568 | M59: 03.444-090 | N59: Vila Nova Manchester | O59: Aricanduva/Formosa/Carrão | P59: Leste | Q59: 2096-4702 | R59: casaderepouso.villadelpozo@gmail.com | T59: 21 | U59: 10 | V59: 6074.2021/0001437-1 | X59: 57
A60: 042.1/15 | B60: 4 (quatro) anos | C60: 47209 | D60: Particular | E60: VIVERE RESIDENCIAL PARA IDOSOS LTDA | F60: VIVERE (MATRIZ) | G60: 04.397.294/0001-98 | H60: 04.397.294/0001-98 | I60: ILPI | J60: 3 | K60: Não | L60: Rua Palacete das Águias, n° 160 | M60: 04635-020 | N60: Vila Alexandria | O60: Santo Amaro | P60: Sul | Q60: (11) 2337-4114 | R60: vivere.residencial160@gmail.com | S60: www.residencialvivere.com.br | T60: 44 | U60: 38 | V60: 6074.2025/0002464-1 | X60: 58
A61: 042.2/15 | B61: 4 (quatro) anos | C61: 47209 | D61: Particular | E61: VIVERE RESIDENCIAL PARA IDOSOS LTDA | F61: VIVERE (FILIAL) | G61: 04.397.294/0002-79 | H61: 04.397.294/0002-79 | I61: ILPI | J61: 3 | K61: Não | L61: Rua Palacete das Águias, n° 169 | M61: 04635-021 | N61: Vila Alexandria | O61: Santo Amaro | P61: Sul | Q61: (11) 2337-4114 | R61: vivere.residencial160@gmail.com | S61: www.residencialvivere.com.br | T61: 27 | U61: 23 | V61: 6074.2025/0002465-0 | X61: 59
A62: 043/15 | B62: NÃO RENOVADO | C62: 43681 | D62: Particular | E62: RESIDÊNCIA DE REPOUSO SAYED LTDA ME ANTIGA:CASA DE REPOUSO SAYED LTDA–ME | F62: CASA DE REPOUSO SAYED LTDA–ME | G62: 05.123.182/0001-01 | I62: ILPI | J62: 3 | K62: Não | O62: Cidade Ademar | P62: Sul | R62: ilham.sayed@hotmail.com | X62: 60
A63: 044/15 | B63: NÃO RENOVADO | C63: 42965 | D63: Particular | E63: CASA DE REPOUSO MODELO LTDA-ME | F63: CASA DE REPOUSO MODELO LTDA-ME | G63: 11.433.191/0001-00 | I63: ILPI | J63: 3 | K63: Não | O63: Lapa | P63: Oeste | R63: NÃO TEM | X63: 61
A64: 045.1/15 | B64: 4 (quatro) anos | C64: 46645 | D64: OSC | E64: ASSOCIAÇÃO BENEFICENTE A MÃO BRANCA DE AMPARO AOS IDOSOS | F64: ILPI - A MÃO BRANCA | G64: 62.299.169/0001-41 | H64: 62.299.169/0001-41 | I64: ILPI | J64: 6 | K64: Não | L64: Avenida Santo Amaro, nº 6487 | M64: 04710-100 | N64: Santo Amaro | O64: Santo Amaro | P64: Sul | Q64: (11) 5523-2055 | R64: amaobranca@amaobranca.org.br | S64: amaobranca@amaobranca.org.br | T64: 118 | U64: 47 | V64: 6074.2023/0008636-8 | X64: 62
A65: 045.2/15 | B65: NÃO RENOVADO | C65: 44850 | D65: OSC | E65: ASSOCIAÇÃO BENEFICENTE A MÃO BRANCA DE AMPARO AOS IDOSOS | F65: NCI - BRÁS | G65: 62.299.169/0001-42 | H65: 62.299.169/0001-41 | I65: NCI | J65: 8 | K65: Não | L65: Rua Polignano Amare, nº 51, Brás, CEP: 03005-040 | O65: Mooca | P65: Leste | Q65: 3228-8114 | R65: amaobranca@amaobranca.org.br | S65: amaobranca@amaobranca.org.br | T65: 100 | U65: 27 | V65: 27 | X65: 63
A66: 045.3/15 | B66: NÃO RENOVADO | C66: 44850 | D66: OSC | E66: ASSOCIAÇÃO BENEFICENTE A MÃO BRANCA DE AMPARO AOS IDOSOS | F66: NCI - A MÃO BRANCA M' BOI MIRIM | G66: 62.299.169/0001-41 | H66: 62.299.169/0001-41 | I66: NCI | J66: 8 | K66: Não | L66: Estrada do M'Boi Mirim, nº 10080 - Jardim ângela - CEP: 04932-060 | O66: M Boi Mirim | P66: Sul | Q66: 5873-7434 | R66: amaobranca@amaobranca.org.br | S66: amaobranca@amaobranca.org.br | T66: 100 | U66: 100 | V66: 100 | X66: 64
A67: 045.4/15 | B67: NÃO RENOVADO | C67: 45581 | D67: OSC | E67: ASSOCIAÇÃO BENEFICENTE A MÃO BRANCA DE AMPARO AOS IDOSOS | F67: NCI - A MÃO BRANCA CAMPO LIMPO | G67: 62.299.169/0001-41 | H67: 62.299.169/0001-41 | I67: NCI | J67: 7 | K67: SMADS | L67: Av. Prof. Leitão da Cunha, nº 15, Pq. Regina - CEP: 05775-200 | O67: Campo Limpo | P67: Sul | Q67: 5842-6327 | R67: amaobranca@amaobranca.org.br | S67: amaobranca@amaobranca.org.br | T67: 100 | U67: 100 | V67: 100 | X67: 65
A68: 045.5/15 | B68: NÃO RENOVADO | C68: 45915 | D68: OSC | E68: ASSOCIAÇÃO BENEFICENTE A MÃO BRANCA DE AMPARO AOS IDOSOS | F68: NCI - A MÃO BRANCA JARDIM ÂNGELA | G68: 62.299.169/0001-41 | H68: 62.299.169/0001-41 | I68: NCI | J68: 8 | K68: Não | L68: Rua Luiz Baldinato, nº 13 | M68: 04935-100 | N68: Capão Redondo | O68: Campo Limpo | P68: Sul | Q68: (11) 5873-7434 | R68: amaobranca@amaobranca.org.br | S68: amaobranca@amaobranca.org.br | T68: 120 | U68: 60 | V68: 6074.2023/0008636-8 | X68: 66
A69: 046/15 | D69: OSC | E69: INSTITUTO VERTER | G69: 07.470.599/0001-76 | H69: 07.470.599/0001-76 | I69: PROJETOS | J69: 12 | K69: Não | O69: Vila Mariana | P69: Sul | R69: rodrigo@institutoverter.com.br | X69: 67
A70: 046.2/15 | B70: 2 (dois) anos | C70: 46389 | D70: OSC | E70: INSTITUTO VERTER | F70: VER NA ESCOLA - MELHOR IDADE | G70: 07.470.599/0001-76 | H70: 07.470.599/0001-76 | I70: PROJETOS | J70: 12 | K70: FMID | L70: DIVERSOS | M70: 01525-001 | N70: Liberdade | O70: Sé | P70: Centro | Q70: (11) 94199-8172 | R70: rosenaide.silva@institutoverter.com.br | S70: www.institutoverter.com.br | T70: 12000 | U70: 12000 | V70: 6074.2024/0010934-3 | X70: 68
A71: 047/15 | B71: 4 (quatro) anos | C71: 47552 | D71: Particular | E71: CASA VIDA – MORADIA ASSISTIDA PARA IDOSOS LTDA | F71: CASA VIDA | G71: 12.395.247/0002-14 | H71: 12.395.247/0002-14 | I71: ILPI | J71: 3 | K71: Não | L71: Rua Irmã Pia, 28 | M71: 05335-050 | N71: Jaguaré | O71: Lapa | P71: Oeste | Q71: (11) 3714-4298 | R71: vidamoradiaassistida@gmail.com | T71: 25 | U71: 23 | V71: 6074.2021/0001900-4 | X71: 69
A72: 048/15 | B72: NÃO RENOVADO | C72: 45655 | D72: OSC | E72: GRUPO DE ARTICULAÇÃO PARA A CONQUISTA DA MORADIA PARA O IDOSO DA CAPITAL | G72: 10.548.116/0001-13 | I72: PROJETOS | J72: 12 | O72: Sé | P72: Centro | R72: garmic@yahoo.com.br | V72: 6074.2022/0009945-0 | X72: 70
A73: 048.2/15 | B73: 2 (dois) anos | C73: 46389 | D73: OSC | E73: GRUPO DE ARTICULAÇÃO PARA A CONQUISTA DA MORADIA PARA O IDOSO DA CAPITAL | F73: CULTURA E MEIO AMBIENTE - FORMAÇÃO DE VÍNCULOS DE CONFIANÇA ATRAVÉS DO EXERCÍCIO DA CIDADANIA | G73: 10.548.116-0001-13 | I73: PROJETOS | J73: 12 | K73: Não | L73: Rua Augusta, 200 (Paque Augusta) | M73: 01305-000 | N73: Consolação | O73: Sé | P73: Centro | Q73: (11) 3101-2277 | R73: garmicmoradiaidoso@gmail.com | S73: - | T73: 120 | U73: 120 | V73: 6074.2024/0010969-6 | X73: 71
A74: 049/15 | B74: 4 (quatro) anos | C74: 47253 | D74: Particular | E74: CASA DE REPOUSO CASA VITA LTDA | F74: CASA VITA | G74: 08.893.447/0001-49 | H74: 08.893.447/0001-49 | I74: ILPI | J74: 3 | K74: Não | L74: Rua Doutor Francisco Pati, 170 | M74: 05352-090 | N74: Vila São Francisco | O74: Butantã | P74: Oeste | Q74: (11) 3766-6978 | R74: qualidade@casavita.com.br | S74: www.casavita.com.br | T74: 42 | U74: 30 | V74: 6074.2019/0003355-0 | X74: 72
A75: 050/15 | B75: 4 (quatro) anos | C75: 47436 | D75: Particular | E75: MM. MARPE CASA DE REPOUSO EIRELI | F75: MARPE CASA DE REPOUSO | G75: 18.288.235/0001-96 | H75: 18.288.235/0001-96 | I75: ILPI | J75: 3 | K75: Não | L75: Rua Baronesa de Bela Vista,nº 88 | M75: 04612-000 | N75: Jd. Aeroporto | O75: Santo Amaro | P75: Sul | Q75: (11) 5565-4943 | R75: marcelogallo01@gmail.com | S75: www.marpecasaderepouso.com.br | T75: 37 | U75: 25 | V75: 6074.2021/0000536-4 | X75: 73
A76: 051/15 | B76: 4 (quatro) anos | C76: 47615 | D76: Particular | E76: RESIDENCIAL GERIÁTRICA ITACOLOMY LTDA | F76: RESIDENCIAL GERIÁTRICA ITACOLOMY | G76: 09.026.019/0001-81 | H76: 09.026.019/0001-81 | I76: ILPI | J76: 3 | K76: Não | L76: Rua Correia Salgado, 224 | M76: 04267-010 | N76: Ipiranga | O76: Ipiranga | P76: Sul | Q76: (11) 2273-6886 | R76: itarepouso@gmail.com | T76: 35 | U76: 25 | V76: 6074.2021/0006387-9 | X76: 74
A77: 052/15 | B77: NÃO RENOVADO | C77: 45259 | D77: Particular | E77: CASA DE REPOUSO E HOSPEDAGEM GERIÁTRICA MANANCIAL LTDA-ME | F77: CASA DE REPOUSO MANANCIAL | G77: 07.947.045/0001-17 | I77: ILPI | J77: 3 | K77: Não | L77: R CAMPOS NOVOS | M77: 03.145-020 | N77: VILA LUCIA | O77: Vila Prudente | P77: Leste | Q77: (11) 2021-8845/ (11) 2021-8845 | R77: iaralogarezzi@hotmail.com | X77: 75
A78: 053/15 | B78: 4 (quatro) anos | C78: 47642 | D78: Particular | E78: GERDIELLE TAMIRES DA CONCEIÇÃO SILVA - ME | F78: CASA DE REPOUSO ANJO GABRIEL | G78: 16.940.588/0001-01 | H78: 16.940.588/0001-01 | I78: ILPI | J78: 3 | K78: Não | L78: Rua das Oiticas, 600 | M78: 04346-090 | N78: Vila Parque Jabaquara | O78: Jabaquara | P78: Sul | Q78: (11) 98868-3584 | R78: anjogabriel_repouso@hotmail.com | S78: www.casaderepousoanjogabriel.com.br | T78: 20 | U78: 17 | V78: 6074.2021/0007499-4 | X78: 76
A79: 054/15 | B79: NÃO RENOVADO | C79: 45833 | D79: Particular | E79: PENSIONATO DA VOVÓ NENA LTDA | F79: PENSIONATO DA VOVÓ NENA | G79: 09.048.917/0001-30 | I79: ILPI | J79: 3 | K79: Não | L79: Rua da Economia, n° 162 | M79: 03532-050 | N79: Vila Matilde | O79: Penha | P79: Leste | Q79: 2654-2378 | R79: pensionatovovonena@hotmail.com | T79: 20 | U79: 14 | V79: 6074.2020/0003702-7 | X79: 77
A80: 055/15 | B80: 4 (quatro) anos | C80: 46320 | D80: Particular | E80: CASA DO IDOSO FELIZ IDADE LTDA | F80: CASA DO IDOSO FELIZ IDADE | G80: 13.590.256/0001-48 | I80: ILPI | J80: 3 | K80: Não | L80: Rua Clarinda Maria de Oliveira, 226 | M80: 02150-020 | N80: Jardim Guança | O80: Vila Maria/Vila Guilherme | P80: Norte | Q80: (11) 2939-1452 | R80: faleconosco@casadoidosofelizidade.com.br / elida_coronado@yahoo.com.br | S80: www.casadoidosofelizidade.com.br | T80: 21 | U80: 19 | V80: 6074.2022/0007126-1 | X80: 78
A81: 056/15 | B81: NÃO RENOVADO | C81: 45802 | D81: Particular | E81: CONSULTÓRIO MÉDICO CASA GERIÁTRICA SILVEIRA E PEREIRA S/S LTDA | G81: 03.763.586/0001-34 | I81: ILPI | J81: 3 | K81: Não | L81: Rua Itabaiana, n° 696 | M81: 03171-010 | N81: Belenzinho | O81: Mooca | P81: Leste | Q81: 2604-6871 | R81: mariacarlotamel@gmail.com | S81: www.clinicacestarisilveira.com.br | T81: 15 | U81: 12 | V81: 12 | X81: 79
A82: 057/15 | B82: NÃO RENOVADO | C82: 43017 | D82: Particular | E82: MORADIA ASSISTIDA PARA IDOSOS SÃO GUALTER LTDA-EPP | F82: MORADIA ASSISTIDA PARA IDOSOS SÃO GUALTER | G82: 15.554.598/0001-38 | I82: ILPI | J82: 3 | K82: Não | O82: Pinheiros | P82: Oeste | R82: ricardovaleriote@uol.com.br | X82: 80
A83: 058/15 | B83: 4 (quatro) anos | C83: 47552 | D83: Particular | E83: CASA DE REPOUSO MORADA DO SOL LTDA | F83: MORADA DO SOL | G83: 45.844.479/0001-80 | H83: 45.844.479/0001-80 | I83: ILPI | J83: 3 | K83: Não | L83: Rua Doutor Candido Espinheira, 412 | M83: 05004-000 | N83: Perdizes | O83: Lapa | P83: Oeste | Q83: (11) 3862-4605 | R83: sonia@residencialemfamilia.com.br | S83: www.casaderepousoemfamilia.com.br | T83: 48 | U83: 39 | V83: 6074.2021/0006254-6 | X83: 81
A84: 059/15 | B84: NÃO RENOVADO | C84: 43747 | D84: Particular | E84: CASA DE REPOUSO HIGIENÓPOLIS LTDA - EPP | G84: 50.587.062/0001-10 | I84: ILPI | J84: 3 | K84: Não | O84: Sé | P84: Centro | Q84: (11) 3663 3827 | R84: crhigienopolis@terra.com.br | X84: 82
A85: 060/15 | B85: 4 (quatro) anos | C85: 47120 | D85: Particular | E85: SOLAR DA MATRIZ REPOUSO PARA IDOSOS S/S LTDA | F85: SOLAR DA MATRIZ | G85: 09.237.774/0001-05 | H85: 09.237.774/0001-05 | I85: ILPI | J85: 3 | K85: Não | L85: Rua Chico de Paulo, 442 | M85: 02926-000 | N85: Freguesia do Ó | O85: Freguesia do Ó/Brasilândia | P85: Norte | Q85: (11) 3932-3015 | R85: solardamatrizidosos@gmail.com | S85: - | T85: 30 | U85: 28 | V85: 6074.2024/0010895-9 | X85: 83
A86: 061/15 | B86: 4 (quatro) anos | C86: 47359 | D86: Particular | E86: RESIDENCIAL AQUARIUS LTDA | F86: RESIDENCIAL AQUARIUS | G86: 04.136.216/0001-30 | H86: 04.136.216/0001-30 | I86: ILPI | J86: 3 | K86: Não | L86: Rua Albina Barbosa, n° 76 | M86: 01530-020 | N86: Aclimação | O86: Sé | P86: Centro | Q86: (11) 3275-0573 / (11) 99127-2489 | R86: aquarius@aquariuscasaderepouso.com.br | S86: www.casaderepousoaquarius.com | T86: 35 | U86: 25 | V86: 6074.2025/0006872-0 | X86: 84
A87: 062/15 | B87: 4 (quatro) anos | C87: 47406 | D87: Particular | E87: QUEIROZ INSTITUIÇÃO PARA IDOSOS LTDA | F87: RESIDENCIA GERIÁTRICA PANAMBY | G87: 20.190.020/0001-80 | H87: 20.190.020/0001-80 | I87: ILPI | J87: 3 | K87: Não | L87: Praça Pinheiro da Cunha, nº 467 | M87: 04275-050 | N87: Vila Dom Predro I | O87: Ipiranga | P87: Sul | Q87: (11) 5061-0364 | R87: geripanam@gmail.com | S87: www.geriatricapanamby.com.br | T87: 26 | U87: 16 | V87: 6074.2025/0008110-6 | X87: 85
A88: 063/15 | B88: 4 (quatro) anos | C88: 46932 | D88: Particular | E88: CASA DE REPOUSO NEW LIFE LTDA–ME | F88: CASA DE REPOUSO NEW LIFE | G88: 08.106.869/0001-27 | H88: 08.106.869/0001-27 | I88: ILPI | J88: 3 | K88: Não | L88: Rua Padre Raposo, nº 272 | M88: 03118-000 | N88: Mooca | O88: Mooca | P88: Leste | Q88: (11) 2081-4493 / (11) 2081-4494 | R88: priscilla@casaderepousonewlife.com.br | S88: www.casaderepousonewlife.com.br | T88: 41 | U88: 41 | V88: 6074.2024/0005995-8 | X88: 86
A89: 063.2/15 | B89: 4 (quatro) anos | C89: 47615 | D89: Particular | E89: CASA DE REPOUSO NEW LIFE LTDA | F89: NEW LIFE RESIDENCIAL SÊNIOR | G89: 08.106.869/0002-08 | H89: 08.106.869/0002-08 | I89: ILPI | J89: 3 | K89: Não | L89: Rua Marquês de Valença, 442/444 | M89: 03182-040 | N89: Mooca | O89: Mooca | P89: Leste | Q89: (11) 2605-2562 | R89: priscilla@casaderepousonewlife.com.br | S89: www.casaderepousonewlife.com.br | T89: 48 | U89: 8 | V89: 6074.2024/0005995-8 | X89: 87
A90: 064/15 | B90: 4 (quatro) anos | C90: 47194 | D90: Particular | E90: C.I.A.I. – CENTRO INTEGRADO DE ATENDIMENTO AO IDOSO LTDA | F90: CORA MORUMBI | G90: 61.056.651/0001-98 | H90: 61.056.651/0001-98 | I90: ILPI | J90: 3 | K90: Não | L90: Rua Alfredo Mendes da Silva, 201 | M90: 05525-000 | N90: Jardim Jussara | O90: Butantã | P90: Oeste | Q90: (11) 3751-4951 | R90: legalizacao@bslsaude.com.br | S90: www.corasenior.com.br/cora-morumbi | T90: 40 | U90: 8 | V90: 6074.2025/0001844-7 | X90: 88
A91: 065/15 | B91: 2 (dois) anos | C91: 46885 | D91: OSC | E91: ASSOCIAÇÃO SUL BRASILEIRA DE EDUCAÇÃO E ASSISTÊNCIA SOCIAL – ASBEAS | F91: CENTRO DE REPOUSO SÃO JOSÉ PEDRO SOARES DE ANDRADE | G91: 15.156.557/0001-93 | H91: 15.156.557/0017-50 | I91: ILPI | J91: 6 | K91: Não | L91: Rua Eulália Felisbela de Oliveira, n° 59 | M91: 08090-020 | N91: Parque Paulistano | O91: São Miguel Paulista | P91: Leste | Q91: (11) 2956-7495 | R91: asbeascrsj@gmail.com | T91: 38 | U91: 35 | V91: 6074.2023/0011855-3 | W91: 6074.2021/0001314-6 | X91: 89
A92: 066/15 | B92: 4 (quatro) anos | C92: 46372 | D92: Particular | E92: RESIDENCIAL VILA HARMONIA PARA IDOSOS EIRELI | F92: RESIDENCIAL VILA HARMONIA LTDA | G92: 17.612.799/0001-70 | I92: ILPI | J92: 3 | K92: Não | L92: Rua Biguaçu, 116 | M92: 03446-000 | N92: Vila Carrão | O92: Aricanduva/Formosa/Carrão | P92: Leste | Q92: 3804-2374 | R92: vilaharmoniaresidencial@gmail.com | S92: www.casaderepousovh.com.br | T92: 38 | U92: 38 | V92: 6074.2022/0008801-6 | X92: 90
A93: 067/15 | B93: NÃO RENOVADO | C93: 45643 | D93: OSC | E93: COMUNIDADE NOVO PENTECOSTES | F93: COMUNIDADE NOVO PENTECOSTES | G93: 01.796.949/0001-02 | I93: ILPI | O93: Butantã | P93: Oeste | R93: dlmaffia@uol.com.br | X93: 91
A94: 068/15 | B94: 4 (quatro) anos | C94: 46617 | D94: Particular | E94: RESIDENCIAL SANTA ISABEL S/S LTDA - ME | F94: RESIDENCIAL SANTA ISABEL | G94: 67.832.550/0001-48 | H94: 67.832.550/0001-48 | I94: ILPI | J94: 3 | K94: Não | L94: Rua Professora Maria de Lourdes Souza Nogueira, n° 189 | M94: 04692-000 | N94: Vila Gea | O94: Santo Amaro | P94: Sul | Q94: 5631-4903 | R94: residencialsantaisabel@hotmail.com | T94: 15 | U94: 11 | V94: 6074.2023/0007788-1 | X94: 92
A95: 069/15 | B95: 2 (dois) anos | C95: 46359 | D95: OSC | E95: FUNDAÇÃO NOSSA SENHORA AUXILIADORA DO IPIRANGA | F95: CENTRO DE CONVIVÊNCIA VIVAVIDA (UNIDADE VI) | G95: 60.737.590/0007-57 | H95: 60.737.590/0007-57 | I95: NCI | J95: 8 | K95: Não | L95: Rua Dom Luis Lasanha, 255 | M95: 04266-030 | N95: Ipiranga | O95: Ipiranga | P95: Sul | Q95: (11) 3806-1151 | R95: funsai@funsai.org.br | S95: www.funsai.org.br | T95: 700 | U95: 657 | V95: 6074.2024/0010095-8 | W95: 6074.2022/0008248-4 | X95: 93
A96: 070/15 | B96: NÃO RENOVADO | C96: 46004 | D96: Particular | E96: EVANDRO GATHAS - ME | F96: RESIDENCIAL HARMONY | G96: 17.812.097/0001-30 | I96: ILPI | J96: 3 | K96: Não | L96: Rua Ovidor Portugal, 131 | M96: 01.551-000 | N96: Vila Monumento | O96: Sé | P96: Centro | Q96: (11) 2293-2855 | R96: residencialharmony@outlook..com | S96: www.casaderepousonoipiranga.com.br | T96: 33 | U96: 29 | V96: 6074.2021/0005599-0 | X96: 94
A97: 071/15 | B97: NÃO RENOVADO | C97: 43809 | D97: Particular | E97: PREVENT SENIOR PRIVATE OPERADORA DE SAÚDE LTDA | F97: COMITÊ DE ÉTICA EM PESQUISA – PESQUISA, COINOVAÇÃO E DIFUSÃO EM GERIATRIA E GERONTOLOGIA | G97: 00.461.479/0001-63 | I97: PROJETOS | J97: 12 | O97: Pinheiros | P97: Oeste | R97: cepps@preventsenior.com.br | X97: 95
A98: 072/15 | B98: 4 (quatro) anos | C98: 47450 | D98: Particular | E98: ELIZABETH MENDONÇAS - ME | F98: HOMER SAÚDE | G98: 12.643.773/0001-75 | H98: 12.643.773/0001-75 | I98: ILPI | J98: 3 | K98: Não | L98: Rua Valentim Magalhães, n° 311 | M98: 03184-090 | N98: Alto da Mooca | O98: Mooca | P98: Leste | Q98: (11) 2507-6422 | R98: homersaude@hotmail.com | T98: 12 | U98: 5 | V98: 6074.2025/0009162-4 | X98: 96
A99: 073/15 | B99: 4 (quatro) anos | C99: 46537 | D99: Particular | E99: CASA DE REPOUSO BELA IDADE – EIRELLI - ME | F99: CASA DE REPOUSO BELA IDADE | G99: 21.583.846/0001-71 | H99: 21.583.846/0001-71 | I99: ILPI | J99: 3 | K99: Não | L99: Avenida Antônio Barbosa da Silva Sandoval, nº 257 | M99: 04783-000 | N99: Interlagos | O99: Capela do Socorro | P99: Sul | Q99: 4562-3100 | R99: contato@casaderepousobelaidade.com.br | S99: www.casaderepousobelaidade.com.br | T99: 19 | U99: 12 | V99: 12 | X99: 97
A100: 074/16 | B100: NÃO RENOVADO | C100: 43147 | D100: Particular | E100: CASA DE REPOUSO ATHENNA EIRELLI - EPP | F100: CASA DE REPOUSO ATHENNA | G100: 02.671.900/0001-96 | I100: ILPI | J100: 3 | K100: Não | L100: Rua Camé, 512 | M100: 03121-020 | N100: Parque da Mooca | O100: Mooca | P100: Leste | Q100: (11) 2021-8954/ (11) 2021-8954 | R100: casaathenna@provencegestao.com.br | X100: 98
...

Sheet TOTAIS
B1: REGIÃO | C1: SUBPREFEITURA | D1: ILPI particular | E1: ILPI conveniada | F1: ILPI não conveniada | G1: CDI particular | H1: CDI conveniado | I1: NCI conveniado | J1: NCI não conveniado | K1: CAEI | L1: CCINTER | M1: TOTAL POR SUBPREF
B2: Leste | C2: Aricanduva/Formosa/Carrão | D2: 48 | E2: 0 | F2: 3 | G2: 0 | H2: 1 | I2: 0 | J2: 0 | K2: 0 | L2: 0 | M2: =SUM(D2:L2) -> 52
B3: Oeste | C3: Butantã | D3: 30 | E3: 0 | F3: 3 | G3: 0 | H3: 1 | I3: 1 | J3: 0 | K3: 0 | L3: 0 | M3: =SUM(D3:L3) -> 35
B4: Sul | C4: Campo Limpo | D4: 9 | E4: 1 | F4: 0 | G4: 0 | H4: 1 | I4: 7 | J4: 4 | K4: 0 | L4: 0 | M4: =SUM(D4:L4) -> 22
B5: Sul | C5: Capela do Socorro | D5: 23 | E5: 1 | F5: 3 | G5: 0 | H5: 1 | I5: 3 | J5: 0 | K5: 1 | L5: 1 | M5: =SUM(D5:L5) -> 33
B6: Norte | C6: Casa Verde/Cachoeirinha/Limão | D6: 9 | E6: 1 | F6: 0 | G6: 0 | H6: 1 | I6: 3 | J6: 2 | K6: 1 | L6: 0 | M6: =SUM(D6:L6) -> 17
B7: Sul | C7: Cidade Ademar | D7: 10 | E7: 0 | F7: 2 | G7: 0 | H7: 0 | I7: 2 | J7: 0 | K7: 1 | L7: 0 | M7: =SUM(D7:L7) -> 15
B8: Leste | C8: Cidade Tiradentes | D8: 0 | E8: 0 | F8: 0 | G8: 0 | H8: 1 | I8: 1 | J8: 0 | K8: 0 | L8: 0 | M8: =SUM(D8:L8) -> 2
B9: Leste | C9: Ermelino Matarazzo | D9: 3 | E9: 0 | F9: 1 | G9: 0 | H9: 1 | I9: 3 | J9: 1 | K9: 0 | L9: 0 | M9: =SUM(D9:L9) -> 9
B10: Norte | C10: Freguesia do Ó/Brasilândia | D10: 8 | E10: 1 | F10: 1 | G10: 0 | H10: 0 | I10: 0 | J10: 3 | K10: 0 | L10: 2 | M10: =SUM(D10:L10) -> 15
B11: Leste | C11: Guaianases | D11: 3 | E11: 0 | F11: 0 | G11: 0 | H11: 0 | I11: 2 | J11: 0 | K11: 0 | L11: 0 | M11: =SUM(D11:L11) -> 5
B12: Sul | C12: Ipiranga | D12: 24 | E12: 0 | F12: 0 | G12: 1 | H12: 1 | I12: 1 | J12: 4 | K12: 0 | L12: 0 | M12: =SUM(D12:L12) -> 31
B13: Leste | C13: Itaim Paulista | D13: 9 | E13: 1 | F13: 7 | G13: 0 | H13: 0 | I13: 4 | J13: 0 | K13: 0 | L13: 0 | M13: =SUM(D13:L13) -> 21
... B33: Leste | C33: Vila Prudente | D33: 19 | E33: 0 | F33: 1 | G33: 0 | H33: 0 | I33: 2 | J33: 3 | K33: 0 | L33: 0 | M33: =SUM(D33:L33) -> 25
C34: TOTAL | D34: =SUM(D2:D33) -> 671 | E34: =SUM(E2:E33) -> 15 | F34: =SUM(F2:F33) -> 48 | G34: =SUM(G2:G33) -> 6 | H34: =SUM(H2:H33) -> 22 | I34: =SUM(I2:I33) -> 70 | J34: =SUM(J2:J33) -> 32 | K34: =SUM(K2:K33) -> 18 | ... M34: =SUM(M2:M33) -> 887
B35: Atualização: 06/05/2026. Base de dados dos registros do Conselho Municipal de Direitos do Idoso da Cidade de São Paulo (CMI/SP). Larissa Rocha
B37: • ILPI - Instituição de Longa Permanência para Idosos
B38: • NCI - Núcleo de Convivência para Idosos
B39: • CDI - Centro Dia para o Idoso
B40: • CAEI - Centro de Acolhida Especial para Idosos
B41: • CCINTER - Centro de Convivência Intergeracional

Sheet Base02
B2: ='Base de Dados'!Y2:Y1392 -> 0 | C2: ='Base de Dados'!D1:D1095 -> MODALIDADE | D2: ='Base de Dados'!F2:F1098 -> NOME FANTASIA | E2: ='Base de Dados'!G2:G683 -> CNPJ Matriz | F2: ='Base de Dados'!I2:I683 -> PROGRAMA
B3: ='Base de Dados'!Y3:Y1393 -> 0 | C3: ='Base de Dados'!E2:E1392 -> ASSOCIAÇÃO SANTO AGOSTINHO - ASA | D3: ='Base de Dados'!F3:F1392 -> CDI LAR SANTO ALBERTO | E3: ='Base de Dados'!G3:G683 -> 62.272.497/0001-54 | F3: ='Base de Dados'!I3:I1098 -> CDI
B4: ='Base de Dados'!Y5:Y1394 -> #VALUE! | C4: ='Base de Dados'!E3:E1393 -> ASSOCIAÇÃO SANTO AGOSTINHO - ASA | D4: ='Base de Dados'!F5:F1393 -> #VALUE! | E4: ='Base de Dados'!G5:G1089 -> #VALUE! | F4: ='Base de Dados'!I5:I1095 -> #VALUE!
B5: ='Base de Dados'!Y6:Y1395 -> #VALUE! | C5: ='Base de Dados'!E5:E1394 -> ASSOCIAÇÃO DOS FAMILIARES E AMIGOS DOS IDOSOS - AFAI | D5: ='Base de Dados'!F6:F1394 -> #VALUE! | E5: ='Base de Dados'!G6:G1095 -> #VALUE! | F5: ='Base de Dados'!I6:I1392 -> #VALUE!
B6: ='Base de Dados'!Y7:Y1396 -> #VALUE! | C6: ='Base de Dados'!E6:E1395 -> ASSOCIAÇÃO FRANCISCANA DE SOLIDARIEDADE | D6: ='Base de Dados'!F7:F1395 -> #VALUE! | E6: ='Base de Dados'!G7:G1392 -> #VALUE! | F6: ='Base de Dados'!I7:I1393 -> #VALUE!
B7: ='Base de Dados'!Y8:Y1397 -> #VALUE! | C7: ='Base de Dados'!E7:E1396 -> ASSOCIAÇÃO FRANCISCANA DE SOLIDARIEDADE - SEFRAS | D7: ='Base de Dados'!F8:F1396 -> #VALUE! | E7: ='Base de Dados'!G8:G1393 -> #VALUE! | F7: ='Base de Dados'!I8:I1394 -> #VALUE!
B8: ='Base de Dados'!Y9:Y1398 -> #VALUE! | C8: ='Base de Dados'!E8:E1397 -> SOCIEDADE BENEFICENTE EQUILIBRIO DE INTERLAGOS - SOBEI | D8: ='Base de Dados'!F9:F1397 -> #VALUE! | E8: ='Base de Dados'!G9:G1394 -> #VALUE! | F8: ='Base de Dados'!I9:I1395 -> #VALUE!
B9: ='Base de Dados'!Y10:Y1399 -> #VALUE! | C9: ='Base de Dados'!E9:E1398 -> SOCIEDADE BENEFICENTE EQUILIBRIO DE INTERLAGOS - SOBEI | D9: ='Base de Dados'!F10:F1398 -> #VALUE! | E9: ='Base de Dados'!G10:G1395 -> #VALUE! | F9: ='Base de Dados'!I10:I1396 -> #VALUE!
B10: ='Base de Dados'!Y12:Y1400 -> #VALUE! | C10: ='Base de Dados'!E10:E1399 -> SOCIEDADE BENEFICENTE EQUILIBRIO DE INTERLAGOS - SOBEI | D10: ='Base de Dados'!F12:F1399 -> #VALUE! | E10: ='Base de Dados'!G12:G1396 -> #VALUE! | F10: ='Base de Dados'!I12:I1397 -> #VALUE!
B11: ='Base de Dados'!Y13:Y1401 -> #VALUE! | C11: ='Base de Dados'!E12:E1400 -> #VALUE! | D11: ='Base de Dados'!F13:F1400 -> #VALUE! | E11: ='Base de Dados'!G13:G1397 -> #VALUE! | F11: ='Base de Dados'!I13:I1398 -> #VALUE!
B12: ='Base de Dados'!Y14:Y1402 -> #VALUE! | C12: ='Base de Dados'!E13:E1401 -> #VALUE! | D12: ='Base de Dados'!F14:F1401 -> #VALUE! | E12: ='Base de Dados'!G14:G1398 -> #VALUE! | F12: ='Base de Dados'!I14:I1399 -> #VALUE!
B13: ='Base de Dados'!Y15:Y1403 -> #VALUE! | C13: ='Base de Dados'!E14:E1402 -> #VALUE! | D13: ='Base de Dados'!F15:F1402 -> #VALUE! | E13: ='Base de Dados'!G15:G1399 -> #VALUE! | F13: ='Base de Dados'!I15:I1400 -> #VALUE!
B14: ='Base de Dados'!Y16:Y1404 -> #VALUE! | C14: ='Base de Dados'!E15:E1403 -> #VALUE! | D14: ='Base de Dados'!F16:F1403 -> #VALUE! | E14: ='Base de Dados'!G16:G1400 -> #VALUE! | F14: ='Base de Dados'!I16:I1401 -> #VALUE!
B15: ='Base de Dados'!Y17:Y1405 -> #VALUE! | C15: ='Base de Dados'!E16:E1404 -> #VALUE! | D15: ='Base de Dados'!F17:F1404 -> #VALUE! | E15: ='Base de Dados'!G17:G1401 -> #VALUE! | F15: ='Base de Dados'!I17:I1402 -> #VALUE!
B16: ='Base de Dados'!Y18:Y1406 -> #VALUE! | C16: ='Base de Dados'!E17:E1405 -> #VALUE! | D16: ='Base de Dados'!F18:F1405 -> #VALUE! | E16: ='Base de Dados'!G18:G1402 -> #VALUE! | F16: ='Base de Dados'!I18:I1403 -> #VALUE!
B17: ='Base de Dados'!Y19:Y1407 -> #VALUE! | C17: ='Base de Dados'!E18:E1406 -> #VALUE! | D17: ='Base de Dados'!F19:F1406 -> #VALUE! | E17: ='Base de Dados'!G19:G1403 -> #VALUE! | F17: ='Base de Dados'!I19:I1404 -> #VALUE!
B18: ='Base de Dados'!Y20:Y1408 -> #VALUE! | C18: ='Base de Dados'!E19:E1407 -> #VALUE! | D18: ='Base de Dados'!F20:F1407 -> #VALUE! | E18: ='Base de Dados'!G20:G1404 -> #VALUE! | F18: ='Base de Dados'!I20:I1405 -> #VALUE!
B19: ='Base de Dados'!Y21:Y1409 -> #VALUE! | C19: ='Base de Dados'!E20:E1408 -> #VALUE! | D19: ='Base de Dados'!F21:F1408 -> #VALUE! | E19: ='Base de Dados'!G21:G1405 -> #VALUE! | F19: ='Base de Dados'!I21:I1406 -> #VALUE!
B20: ='Base de Dados'!Y22:Y1410 -> #VALUE! | C20: ='Base de Dados'!E21:E1409 -> #VALUE! | D20: ='Base de Dados'!F22:F1409 -> #VALUE! | E20: ='Base de Dados'!G22:G1406 -> #VALUE! | F20: ='Base de Dados'!I22:I1407 -> #VALUE!
B21: ='Base de Dados'!Y23:Y1411 -> #VALUE! | C21: ='Base de Dados'!E22:E1410 -> #VALUE! | D21: ='Base de Dados'!F23:F1410 -> #VALUE! | E21: ='Base de Dados'!G23:G1407 -> #VALUE! | F21: ='Base de Dados'!I23:I1408 -> #VALUE!
B22: ='Base de Dados'!Y24:Y1412 -> #VALUE! | C22: ='Base de Dados'!E23:E1411 -> #VALUE! | D22: ='Base de Dados'!F24:F1411 -> #VALUE! | E22: ='Base de Dados'!G24:G1408 -> #VALUE! | F22: ='Base de Dados'!I24:I1409 -> #VALUE!
... B31: ='Base de Dados'!Y33:Y1421 -> #VALUE! | C31: ='Base de Dados'!E32:E1420 -> #VALUE! | D31: ='Base de Dados'!F33:F1420 -> #VALUE! | E31: ='Base de Dados'!G33:G1417 -> #VALUE! | F31: ='Base de Dados'!I33:I1418 -> #VALUE!
B32: ='Base de Dados'!Y36:Y1422 -> #VALUE! | C32: ='Base de Dados'!E33:E1421 -> #VALUE! | D32: ='Base de Dados'!F36:F1421 -> #VALUE! | E32: ='Base de Dados'!G36:G1418 -> #VALUE! | F32: ='Base de Dados'!I36:I1419 -> #VALUE!
B33: ='Base de Dados'!Y37:Y1423 -> #VALUE! | C33: ='Base de Dados'!E36:E1422 -> #VALUE! | D33: ='Base de Dados'!F37:F1422 -> #VALUE! | E33: ='Base de Dados'!G37:G1419 -> #VALUE! | F33: ='Base de Dados'!I37:I1420 -> #VALUE!
B34: ='Base de Dados'!Y38:Y1424 -> #VALUE! | C34: ='Base de Dados'!E37:E1423 -> #VALUE! | D34: ='Base de Dados'!F38:F1423 -> #VALUE! | E34: ='Base de Dados'!G38:G1420 -> #VALUE! | F34: ='Base de Dados'!I38:I1421 -> #VALUE!
B35: ='Base de Dados'!Y39:Y1425 -> #VALUE! | C35: ='Base de Dados'!E38:E1424 -> #VALUE! | D35: ='Base de Dados'!F39:F1424 -> #VALUE! | E35: ='Base de Dados'!G39:G1421 -> #VALUE! | F35: ='Base de Dados'!I39:I1422 -> #VALUE!
B36: ='Base de Dados'!Y40:Y1426 -> #VALUE! | C36: ='Base de Dados'!E39:E1425 -> #VALUE! | D36: ='Base de Dados'!F40:F1425 -> #VALUE! | E36: ='Base de Dados'!G40:G1422 -> #VALUE! | F36: ='Base de Dados'!I40:I1423 -> #VALUE!
B37: ='Base de Dados'!Y41:Y1427 -> #VALUE! | C37: ='Base de Dados'!E40:E1426 -> #VALUE! | D37: ='Base de Dados'!F41:F1426 -> #VALUE! | E37: ='Base de Dados'!G41:G1423 -> #VALUE! | F37: ='Base de Dados'!I41:I1424 -> #VALUE!
B38: ='Base de Dados'!Y42:Y1428 -> #VALUE! | C38: ='Base de Dados'!E41:E1427 -> #VALUE! | D38: ='Base de Dados'!F42:F1427 -> #VALUE! | E38: ='Base de Dados'!G42:G1424 -> #VALUE! | F38: ='Base de Dados'!I42:I1425 -> #VALUE!
B39: ='Base de Dados'!Y43:Y1429 -> #VALUE! | C39: ='Base de Dados'!E42:E1428 -> #VALUE! | D39: ='Base de Dados'!F43:F1428 -> #VALUE! | E39: ='Base de Dados'!G43:G1425 -> #VALUE! | F39: ='Base de Dados'!I43:I1426 -> #VALUE!
B40: ='Base de Dados'!Y44:Y1430 -> #VALUE! | C40: ='Base de Dados'!E43:E1429 -> #VALUE! | D40: ='Base de Dados'!F44:F1429 -> #VALUE! | E40: ='Base de Dados'!G44:G1426 -> #VALUE! | F40: ='Base de Dados'!I44:I1427 -> #VALUE!
B41: ='Base de Dados'!Y45:Y1431 -> #VALUE! | C41: ='Base de Dados'!E44:E1430 -> #VALUE! | D41: ='Base de Dados'!F45:F1430 -> #VALUE! | E41: ='Base de Dados'!G45:G1427 -> #VALUE! | F41: ='Base de Dados'!I45:I1428 -> #VALUE!
B42: ='Base de Dados'!Y46:Y1432 -> #VALUE! | C42: ='Base de Dados'!E45:E1431 -> #VALUE! | D42: ='Base de Dados'!F46:F1431 -> #VALUE! | E42: ='Base de Dados'!G46:G1428 -> #VALUE! | F42: ='Base de Dados'!I46:I1429 -> #VALUE!
B43: ='Base de Dados'!Y47:Y1433 -> #VALUE! | C43: ='Base de Dados'!E46:E1432 -> #VALUE! | D43: ='Base de Dados'!F47:F1432 -> #VALUE! | E43: ='Base de Dados'!G47:G1429 -> #VALUE! | F43: ='Base de Dados'!I47:I1430 -> #VALUE!
B44: ='Base de Dados'!Y48:Y1434 -> #VALUE! | C44: ='Base de Dados'!E47:E1433 -> #VALUE! | D44: ='Base de Dados'!F48:F1433 -> #VALUE! | E44: ='Base de Dados'!G48:G1430 -> #VALUE! | F44: ='Base de Dados'!I48:I1431 -> #VALUE!
... B51: ='Base de Dados'!Y55:Y1441 -> #VALUE! | C51: ='Base de Dados'!E54:E1440 -> #VALUE! | D51: ='Base de Dados'!F55:F1440 -> #VALUE! | E51: ='Base de Dados'!G55:G1437 -> #VALUE! | F51: ='Base de Dados'!I55:I1438 -> #VALUE!
B52: ='Base de Dados'!Y57:Y1442 -> #VALUE! | C52: ='Base de Dados'!E55:E1441 -> #VALUE! | D52: ='Base de Dados'!F57:F1441 -> #VALUE! | E52: ='Base de Dados'!G57:G1438 -> #VALUE! | F52: ='Base de Dados'!I57:I1439 -> #VALUE!
B53: ='Base de Dados'!Y58:Y1443 -> #VALUE! | C53: ='Base de Dados'!E57:E1442 -> #VALUE! | D53: ='Base de Dados'!F58:F1442 -> #VALUE! | E53: ='Base de Dados'!G58:G1439 -> #VALUE! | F53: ='Base de Dados'!I58:I1440 -> #VALUE!
B54: ='Base de Dados'!Y59:Y1444 -> #VALUE! | C54: ='Base de Dados'!E58:E1443 -> #VALUE! | D54: ='Base de Dados'!F59:F1443 -> #VALUE! | E54: ='Base de Dados'!G59:G1440 -> #VALUE! | F54: ='Base de Dados'!I59:I1441 -> #VALUE!
B55: ='Base de Dados'!Y60:Y1445 -> #VALUE! | C55: ='Base de Dados'!E59:E1444 -> #VALUE! | D55: ='Base de Dados'!F60:F1444 -> #VALUE! | E55: ='Base de Dados'!G60:G1441 -> #VALUE! | F55: ='Base de Dados'!I60:I1442 -> #VALUE!
B56: ='Base de Dados'!Y62:Y1446 -> #VALUE! | C56: ='Base de Dados'!E60:E1445 -> #VALUE! | D56: ='Base de Dados'!F62:F1445 -> #VALUE! | E56: ='Base de Dados'!G62:G1442 -> #VALUE! | F56: ='Base de Dados'!I62:I1443 -> #VALUE!
B57: ='Base de Dados'!Y63:Y1447 -> #VALUE! | C57: ='Base de Dados'!E62:E1446 -> #VALUE! | D57: ='Base de Dados'!F63:F1446 -> #VALUE! | E57: ='Base de Dados'!G63:G1443 -> #VALUE! | F57: ='Base de Dados'!I63:I1444 -> #VALUE!
B58: ='Base de Dados'!Y64:Y1448 -> #VALUE! | C58: ='Base de Dados'!E63:E1447 -> #VALUE! | D58: ='Base de Dados'!F64:F1447 -> #VALUE! | E58: ='Base de Dados'!G64:G1444 -> #VALUE! | F58: ='Base de Dados'!I64:I1445 -> #VALUE!
B59: ='Base de Dados'!Y67:Y1449 -> #VALUE! | C59: ='Base de Dados'!E64:E1448 -> #VALUE! | D59: ='Base de Dados'!F67:F1448 -> #VALUE! | E59: ='Base de Dados'!G67:G1445 -> #VALUE! | F59: ='Base de Dados'!I67:I1446 -> #VALUE!
B60: ='Base de Dados'!Y67:Y1450 -> #VALUE! | C60: ='Base de Dados'!E67:E1449 -> #VALUE! | D60: ='Base de Dados'!F67:F1449 -> #VALUE! | E60: ='Base de Dados'!G67:G1446 -> #VALUE! | F60: ='Base de Dados'!I67:I1447 -> #VALUE!
B61: ='Base de Dados'!Y68:Y1451 -> #VALUE! | C61: ='Base de Dados'!E67:E1450 -> #VALUE! | D61: ='Base de Dados'!F68:F1450 -> #VALUE! | E61: ='Base de Dados'!G68:G1447 -> #VALUE! | F61: ='Base de Dados'!I68:I1448 -> #VALUE!
B62: ='Base de Dados'!Y69:Y1452 -> #VALUE! | C62: ='Base de Dados'!E68:E1451 -> #VALUE! | D62: ='Base de Dados'!F69:F1451 -> #VALUE! | E62: ='Base de Dados'!G69:G1448 -> #VALUE! | F62: ='Base de Dados'!I69:I1449 -> #VALUE!
B63: ='Base de Dados'!Y71:Y1453 -> #VALUE! | C63: ='Base de Dados'!E69:E1452 -> #VALUE! | D63: ='Base de Dados'!F71:F1452 -> #VALUE! | E63: ='Base de Dados'!G71:G1449 -> #VALUE! | F63: ='Base de Dados'!I71:I1450 -> #VALUE!
B64: ='Base de Dados'!Y72:Y1454 -> #VALUE! | C64: ='Base de Dados'!E71:E1453 -> #VALUE! | D64: ='Base de Dados'!F72:F1453 -> #VALUE! | E64: ='Base de Dados'!G72:G1450 -> #VALUE! | F64: ='Base de Dados'!I72:I1451 -> #VALUE!
B65: ='Base de Dados'!Y74:Y1455 -> #VALUE! | C65: ='Base de Dados'!E72:E1454 -> #VALUE! | D65: ='Base de Dados'!F74:F1454 -> #VALUE! | E65: ='Base de Dados'!G74:G1451 -> #VALUE! | F65: ='Base de Dados'!I74:I1452 -> #VALUE!
B66: ='Base de Dados'!Y75:Y1456 -> #VALUE! | C66: ='Base de Dados'!E74:E1455 -> #VALUE! | D66: ='Base de Dados'!F75:F1455 -> #VALUE! | E66: ='Base de Dados'!G75:G1452 -> #VALUE! | F66: ='Base de Dados'!I75:I1453 -> #VALUE!
B67: ='Base de Dados'!Y76:Y1457 -> #VALUE! | C67: ='Base de Dados'!E75:E1456 -> #VALUE! | D67: ='Base de Dados'!F76:F1456 -> #VALUE! | E67: ='Base de Dados'!G76:G1453 -> #VALUE! | F67: ='Base de Dados'!I76:I1454 -> #VALUE!
B68: ='Base de Dados'!Y77:Y1458 -> #VALUE! | C68: ='Base de Dados'!E76:E1457 -> #VALUE! | D68: ='Base de Dados'!F77:F1457 -> #VALUE! | E68: ='Base de Dados'!G77:G1454 -> #VALUE! | F68: ='Base de Dados'!I77:I1455 -> #VALUE!
B69: ='Base de Dados'!Y78:Y1459 -> #VALUE! | C69: ='Base de Dados'!E77:E1458 -> #VALUE! | D69: ='Base de Dados'!F78:F1458 -> #VALUE! | E69: ='Base de Dados'!G78:G1455 -> #VALUE! | F69: ='Base de Dados'!I78:I1456 -> #VALUE!
B70: ='Base de Dados'!Y79:Y1460 -> #VALUE! | C70: ='Base de Dados'!E78:E1459 -> #VALUE! | D70: ='Base de Dados'!F79:F1459 -> #VALUE! | E70: ='Base de Dados'!G79:G1456 -> #VALUE! | F70: ='Base de Dados'!I79:I1457 -> #VALUE!
B71: ='Base de Dados'!Y80:Y1461 -> #VALUE! | C71: ='Base de Dados'!E79:E1460 -> #VALUE! | D71: ='Base de Dados'!F80:F1460 -> #VALUE! | E71: ='Base de Dados'!G80:G1457 -> #VALUE! | F71: ='Base de Dados'!I80:I1458 -> #VALUE!
B72: ='Base de Dados'!Y81:Y1462 -> #VALUE! | C72: ='Base de Dados'!E80:E1461 -> #VALUE! | D72: ='Base de Dados'!F81:F1461 -> #VALUE! | E72: ='Base de Dados'!G81:G1458 -> #VALUE! | F72: ='Base de Dados'!I81:I1459 -> #VALUE!
B73: ='Base de Dados'!Y82:Y1463 -> #VALUE! | C73: ='Base de Dados'!E81:E1462 -> #VALUE! | D73: ='Base de Dados'!F82:F1462 -> #VALUE! | E73: ='Base de Dados'!G82:G1459 -> #VALUE! | F73: ='Base de Dados'!I82:I1460 -> #VALUE!
B74: ='Base de Dados'!Y83:Y1464 -> #VALUE! | C74: ='Base de Dados'!E82:E1463 -> #VALUE! | D74: ='Base de Dados'!F83:F1463 -> #VALUE! | E74: ='Base de Dados'!G83:G1460 -> #VALUE! | F74: ='Base de Dados'!I83:I1461 -> #VALUE!
B75: ='Base de Dados'!Y84:Y1465 -> #VALUE! | C75: ='Base de Dados'!E83:E1464 -> #VALUE! | D75: ='Base de Dados'!F84:F1464 -> #VALUE! | E75: ='Base de Dados'!G84:G1461 -> #VALUE! | F75: ='Base de Dados'!I84:I1462 -> #VALUE!
B76: ='Base de Dados'!Y85:Y1466 -> #VALUE! | C76: ='Base de Dados'!E84:E1465 -> #VALUE! | D76: ='Base de Dados'!F85:F1465 -> #VALUE! | E76: ='Base de Dados'!G85:G1462 -> #VALUE! | F76: ='Base de Dados'!I85:I1463 -> #VALUE!
B77: ='Base de Dados'!Y86:Y1467 -> #VALUE! | C77: ='Base de Dados'!E85:E1466 -> #VALUE! | D77: ='Base de Dados'!F86:F1466 -> #VALUE! | E77: ='Base de Dados'!G86:G1463 -> #VALUE! | F77: ='Base de Dados'!I86:I1464 -> #VALUE!
... B79: ='Base de Dados'!Y88:Y1469 -> #VALUE! | C79: ='Base de Dados'!E87:E1468 -> #VALUE! | D79: ='Base de Dados'!F88:F1468 -> #VALUE! | E79: ='Base de Dados'!G88:G1465 -> #VALUE! | F79: ='Base de Dados'!I88:I1466 -> #VALUE!
B80: ='Base de Dados'!Y90:Y1470 -> #VALUE! | C80: ='Base de Dados'!E88:E1469 -> #VALUE! | D80: ='Base de Dados'!F90:F1469 -> #VALUE! | E80: ='Base de Dados'!G90:G1466 -> #VALUE! | F80: ='Base de Dados'!I90:I1467 -> #VALUE!
B81: ='Base de Dados'!Y91:Y1471 -> #VALUE! | C81: ='Base de Dados'!E90:E1470 -> #VALUE! | D81: ='Base de Dados'!F91:F1470 -> #VALUE! | E81: ='Base de Dados'!G91:G1467 -> #VALUE! | F81: ='Base de Dados'!I91:I1468 -> #VALUE!
B82: ='Base de Dados'!Y92:Y1472 -> #VALUE! | C82: ='Base de Dados'!E91:E1471 -> #VALUE! | D82: ='Base de Dados'!F92:F1471 -> #VALUE! | E82: ='Base de Dados'!G92:G1468 -> #VALUE! | F82: ='Base de Dados'!I92:I1469 -> #VALUE!
B83: ='Base de Dados'!Y93:Y1473 -> #VALUE! | C83: ='Base de Dados'!E92:E1472 -> #VALUE! | D83: ='Base de Dados'!F93:F1472 -> #VALUE! | E83: ='Base de Dados'!G93:G1469 -> #VALUE! | F83: ='Base de Dados'!I93:I1470 -> #VALUE!
B84: ='Base de Dados'!Y94:Y1474 -> #VALUE! | C84: ='Base de Dados'!E93:E1473 -> #VALUE! | D84: ='Base de Dados'!F94:F1473 -> #VALUE! | E84: ='Base de Dados'!G94:G1470 -> #VALUE! | F84: ='Base de Dados'!I94:I1471 -> #VALUE!
B85: ='Base de Dados'!Y95:Y1475 -> #VALUE! | C85: ='Base de Dados'!E94:E1474 -> #VALUE! | D85: ='Base de Dados'!F95:F1474 -> #VALUE! | E85: ='Base de Dados'!G95:G1471 -> #VALUE! | F85: ='Base de Dados'!I95:I1472 -> #VALUE!
B86: ='Base de Dados'!Y96:Y1476 -> #VALUE! | C86: ='Base de Dados'!E95:E1475 -> #VALUE! | D86: ='Base de Dados'!F96:F1475 -> #VALUE! | E86: ='Base de Dados'!G96:G1472 -> #VALUE! | F86: ='Base de Dados'!I96:I1473 -> #VALUE!
B87: ='Base de Dados'!Y97:Y1477 -> #VALUE! | C87: ='Base de Dados'!E96:E1476 -> #VALUE! | D87: ='Base de Dados'!F97:F1476 -> #VALUE! | E87: ='Base de Dados'!G97:G1473 -> #VALUE! | F87: ='Base de Dados'!I97:I1474 -> #VALUE!
B88: ='Base de Dados'!Y98:Y1478 -> #VALUE! | C88: ='Base de Dados'!E97:E1477 -> #VALUE! | D88: ='Base de Dados'!F98:F1477 -> #VALUE! | E88: ='Base de Dados'!G98:G1474 -> #VALUE! | F88: ='Base de Dados'!I98:I1475 -> #VALUE!
B89: ='Base de Dados'!Y99:Y1479 -> #VALUE! | C89: ='Base de Dados'!E98:E1478 -> #VALUE! | D89: ='Base de Dados'!F99:F1478 -> #VALUE! | E89: ='Base de Dados'!G99:G1475 -> #VALUE! | F89: ='Base de Dados'!I99:I1476 -> #VALUE!
B90: ='Base de Dados'!Y100:Y1480 -> #VALUE! | C90: ='Base de Dados'!E99:E1479 -> #VALUE! | D90: ='Base de Dados'!F100:F1479 -> #VALUE! | E90: ='Base de Dados'!G100:G1476 -> #VALUE! | F90: ='Base de Dados'!I100:I1477 -> #VALUE!
B91: ='Base de Dados'!Y101:Y1481 -> #VALUE! | C91: ='Base de Dados'!E100:E1480 -> #VALUE! | D91: ='Base de Dados'!F101:F1480 -> #VALUE! | E91: ='Base de Dados'!G101:G1477 -> #VALUE! | F91: ='Base de Dados'!I101:I1478 -> #VALUE!
B92: ='Base de Dados'!Y102:Y1482 -> #VALUE! | C92: ='Base de Dados'!E101:E1481 -> #VALUE! | D92: ='Base de Dados'!F102:F1481 -> #VALUE! | E92: ='Base de Dados'!G102:G1478 -> #VALUE! | F92: ='Base de Dados'!I102:I1479 -> #VALUE!
B93: ='Base de Dados'!Y103:Y1483 -> #VALUE! | C93: ='Base de Dados'!E102:E1482 -> #VALUE! | D93: ='Base de Dados'!F103:F1482 -> #VALUE! | E93: ='Base de Dados'!G103:G1479 -> #VALUE! | F93: ='Base de Dados'!I103:I1480 -> #VALUE!
B94: ='Base de Dados'!Y105:Y1484 -> #VALUE! | C94: ='Base de Dados'!E103:E1483 -> #VALUE! | D94: ='Base de Dados'!F105:F1483 -> #VALUE! | E94: ='Base de Dados'!G105:G1480 -> #VALUE! | F94: ='Base de Dados'!I105:I1481 -> #VALUE!
B95: ='Base de Dados'!Y106:Y1485 -> #VALUE! | C95: ='Base de Dados'!E105:E1484 -> #VALUE! | D95: ='Base de Dados'!F106:F1484 -> #VALUE! | E95: ='Base de Dados'!G106:G1481 -> #VALUE! | F95: ='Base de Dados'!I106:I1482 -> #VALUE!
B96: ='Base de Dados'!Y107:Y1486 -> #VALUE! | C96: ='Base de Dados'!E106:E1485 -> #VALUE! | D96: ='Base de Dados'!F107:F1485 -> #VALUE! | E96: ='Base de Dados'!G107:G1482 -> #VALUE! | F96: ='Base de Dados'!I107:I1483 -> #VALUE!
B97: ='Base de Dados'!Y109:Y1487 -> #VALUE! | C97: ='Base de Dados'!E107:E1486 -> #VALUE! | D97: ='Base de Dados'!F109:F1486 -> #VALUE! | E97: ='Base de Dados'!G109:G1483 -> #VALUE! | F97: ='Base de Dados'!I109:I1484 -> #VALUE!
B98: ='Base de Dados'!Y110:Y1488 -> #VALUE! | C98: ='Base de Dados'!E109:E1487 -> #VALUE! | D98: ='Base de Dados'!F110:F1487 -> #VALUE! | E98: ='Base de Dados'!G110:G1484 -> #VALUE! | F98: ='Base de Dados'!I110:I1485 -> #VALUE!
B99: ='Base de Dados'!Y111:Y1489 -> #VALUE! | C99: ='Base de Dados'!E110:E1488 -> #VALUE! | D99: ='Base de Dados'!F111:F1488 -> #VALUE! | E99: ='Base de Dados'!G111:G1485 -> #VALUE! | F99: ='Base de Dados'!I111:I1486 -> #VALUE!
B100: ='Base de Dados'!Y113:Y1490 -> #VALUE! | C100: ='Base de Dados'!E111:E1489 -> #VALUE! | D100: ='Base de Dados'!F113:F1489 -> #VALUE! | E100: ='Base de Dados'!G113:G1486 -> #VALUE! | F100: ='Base de Dados'!I113:I1487 -> #VALUE!
B101: ='Base de Dados'!Y114:Y1491 -> #VALUE! | C101: ='Base de Dados'!E113:E1490 -> #VALUE! | D101: ='Base de Dados'!F114:F1490 -> #VALUE! | E101: ='Base de Dados'!G114:G1487 -> #VALUE! | F101: ='Base de Dados'!I114:I1488 -> #VALUE!
B102: ='Base de Dados'!Y115:Y1492 -> #VALUE! | C102: ='Base de Dados'!E114:E1491 -> #VALUE! | D102: ='Base de Dados'!F115:F1491 -> #VALUE! | E102: ='Base de Dados'!G115:G1488 -> #VALUE! | F102: ='Base de Dados'!I115:I1489 -> #VALUE!
B103: ='Base de Dados'!Y116:Y1493 -> #VALUE! | C103: ='Base de Dados'!E115:E1492 -> #VALUE! | D103: ='Base de Dados'!F116:F1492 -> #VALUE! | E103: ='Base de Dados'!G116:G1489 -> #VALUE! | F103: ='Base de Dados'!I116:I1490 -> #VALUE!
B104: ='Base de Dados'!Y117:Y1494 -> #VALUE! | C104: ='Base de Dados'!E116:E1493 -> #VALUE! | D104: ='Base de Dados'!F117:F1493 -> #VALUE! | E104: ='Base de Dados'!G117:G1490 -> #VALUE! | F104: ='Base de Dados'!I117:I1491 -> #VALUE!
B105: ='Base de Dados'!Y118:Y1495 -> #VALUE! | C105: ='Base de Dados'!E117:E1494 -> #VALUE! | D105: ='Base de Dados'!F118:F1494 -> #VALUE! | E105: ='Base de Dados'!G118:G1491 -> #VALUE! | F105: ='Base de Dados'!I118:I1492 -> #VALUE!
B106: ='Base de Dados'!Y119:Y1496 -> #VALUE! | C106: ='Base de Dados'!E118:E1495 -> #VALUE! | D106: ='Base de Dados'!F119:F1495 -> #VALUE! | E106: ='Base de Dados'!G119:G1492 -> #VALUE! | F106: ='Base de Dados'!I119:I1493 -> #VALUE!
B107: ='Base de Dados'!Y120:Y1497 -> #VALUE! | C107: ='Base de Dados'!E119:E1496 -> #VALUE! | D107: ='Base de Dados'!F120:F1496 -> #VALUE! | E107: ='Base de Dados'!G120:G1493 -> #VALUE! | F107: ='Base de Dados'!I120:I1494 -> #VALUE!
B108: ='Base de Dados'!Y121:Y1498 -> #VALUE! | C108: ='Base de Dados'!E120:E1497 -> #VALUE! | D108: ='Base de Dados'!F121:F1497 -> #VALUE! | E108: ='Base de Dados'!G121:G1494 -> #VALUE! | F108: ='Base de Dados'!I121:I1495 -> #VALUE!
B109: ='Base de Dados'!Y122:Y1499 -> #VALUE! | C109: ='Base de Dados'!E121:E1498 -> #VALUE! | D109: ='Base de Dados'!F122:F1498 -> #VALUE! | E109: ='Base de Dados'!G122:G1495 -> #VALUE! | F109: ='Base de Dados'!I122:I1496 -> #VALUE!
B110: ='Base de Dados'!Y123:Y1500 -> #VALUE! | C110: ='Base de Dados'!E122:E1499 -> #VALUE! | D110: ='Base de Dados'!F123:F1499 -> #VALUE! | E110: ='Base de Dados'!G123:G1496 -> #VALUE! | F110: ='Base de Dados'!I123:I1497 -> #VALUE!
B111: ='Base de Dados'!Y124:Y1501 -> #VALUE! | C111: ='Base de Dados'!E123:E1500 -> #VALUE! | D111: ='Base de Dados'!F124:F1500 -> #VALUE! | E111: ='Base de Dados'!G124:G1497 -> #VALUE! | F111: ='Base de Dados'!I124:I1498 -> #VALUE!
B112: ='Base de Dados'!Y125:Y1502 -> #VALUE! | C112: ='Base de Dados'!E124:E1501 -> #VALUE! | D112: ='Base de Dados'!F125:F1501 -> #VALUE! | E112: ='Base de Dados'!G125:G1498 -> #VALUE! | F112: ='Base de Dados'!I125:I1499 -> #VALUE!
... B129: ='Base de Dados'!Y142:Y1519 -> #VALUE! | C129: ='Base de Dados'!E141:E1518 -> #VALUE! | D129: ='Base de Dados'!F142:F1518 -> #VALUE! | E129: ='Base de Dados'!G142:G1515 -> #VALUE! | F129: ='Base de Dados'!I142:I1516 -> #VALUE!
B130: ='Base de Dados'!Y147:Y1520 -> #VALUE! | C130: ='Base de Dados'!E142:E1519 -> #VALUE! | D130: ='Base de Dados'!F147:F1519 -> #VALUE! | E130: ='Base de Dados'!G147:G1516 -> #VALUE! | F130: ='Base de Dados'!I147:I1517 -> #VALUE!
B131: ='Base de Dados'!Y148:Y1521 -> #VALUE! | C131: ='Base de Dados'!E147:E1520 -> #VALUE! | D131: ='Base de Dados'!F148:F1520 -> #VALUE! | E131: ='Base de Dados'!G148:G1517 -> #VALUE! | F131: ='Base de Dados'!I148:I1518 -> #VALUE!
B132: ='Base de Dados'!Y149:Y1522 -> #VALUE! | C132: ='Base de Dados'!E148:E1521 -> #VALUE! | D132: ='Base de Dados'!F149:F1521 -> #VALUE! | E132: ='Base de Dados'!G149:G1518 -> #VALUE! | F132: ='Base de Dados'!I149:I1519 -> #VALUE!
...

Sheet Plan1
A3: Rótulos de Linha
A4: 001/12
A5: Associação Santo Agostinho - ASA.
A6: 62.272.497/0001-54
A7: 0010/13
A8: UNIGER - Unidade de Internação Geriátrica LTDA
A9: 07.463.596/0001-05
A10: 0011/14
A11: Sindicato Nacional dos Aposentados, Pensionistas e Idosos da Força Sindical
A12: 04.040.532/0001-03
A13: 0012/14
A14: Casa de Repouso para Idosos Residencial Harmonia LTDA. - Unidade I
... A1201: Total geral

Sheet Plan4
A1: REGISTRO | B1: 0017/14
A3: Rótulos de Linha
A4: Residencial Alto da Boa Vista para Idosos LTDA - ME
A5: 10.248.923/0001-10
A6: Total geral

Sheet Serviços por Região
A3: Rótulos de Linha | B3: Contar de REGISTRO
A4: Centro | B4: 24
A5: Leste | B5: 126
A6: Leste | B6: 2
A7: Norte | B7: 74
A8: Oeste | B8: 54
A9: SEM EFEITO | B9: 1
A10: Sul | B10: 129
A11: Sul | B11: 4
A12: (vazio) | B12: 9
A13: CENTRO DIA | B13: 2
A14: EDEM CENTRO DE CONVIVÊNCIA E CENTRO DIA PARA IDOSOS LTDA | B14: 1
A15: (vazio) | B15: 1
... A20: Total Geral | B20: 423
